{
"meta":{"test_sets":[],"test_metrics":[],"learn_metrics":[{"best_value":"Min","name":"RMSE"}],"launch_mode":"Train","parameters":"","iteration_count":1000,"learn_sets":["learn"],"name":"experiment"},
"iterations":[
{"learn":[165.3844195],"iteration":0,"passed_time":0.0535688207,"remaining_time":53.51525188},
{"learn":[161.9971419],"iteration":1,"passed_time":0.05802685064,"remaining_time":28.95539847},
{"learn":[158.8793546],"iteration":2,"passed_time":0.05985210024,"remaining_time":19.89084798},
{"learn":[155.7168294],"iteration":3,"passed_time":0.06165552287,"remaining_time":15.35222519},
{"learn":[152.9029112],"iteration":4,"passed_time":0.06344626716,"remaining_time":12.62580716},
{"learn":[150.0580716],"iteration":5,"passed_time":0.06522650384,"remaining_time":10.80585747},
{"learn":[147.6194571],"iteration":6,"passed_time":0.06698719841,"remaining_time":9.502612575},
{"learn":[145.1434475],"iteration":7,"passed_time":0.06874957135,"remaining_time":8.524946848},
{"learn":[142.852439],"iteration":8,"passed_time":0.07053796106,"remaining_time":7.767013268},
{"learn":[140.6876336],"iteration":9,"passed_time":0.07232496042,"remaining_time":7.160171081},
{"learn":[138.8252323],"iteration":10,"passed_time":0.07410703318,"remaining_time":6.662895983},
{"learn":[137.1597235],"iteration":11,"passed_time":0.07587779444,"remaining_time":6.247271742},
{"learn":[135.6012248],"iteration":12,"passed_time":0.0776368686,"remaining_time":5.894429947},
{"learn":[134.0431862],"iteration":13,"passed_time":0.07940471757,"remaining_time":5.592360823},
{"learn":[132.5685791],"iteration":14,"passed_time":0.08120333647,"remaining_time":5.332352429},
{"learn":[131.1361866],"iteration":15,"passed_time":0.08295651154,"remaining_time":5.10182546},
{"learn":[129.7777121],"iteration":16,"passed_time":0.08473858431,"remaining_time":4.899884022},
{"learn":[128.6747102],"iteration":17,"passed_time":0.08648431524,"remaining_time":4.718199865},
{"learn":[127.5621403],"iteration":18,"passed_time":0.08821101561,"remaining_time":4.554474016},
{"learn":[126.5165557],"iteration":19,"passed_time":0.08995281294,"remaining_time":4.407687834},
{"learn":[125.5106666],"iteration":20,"passed_time":0.09173510313,"remaining_time":4.276603141},
{"learn":[124.5876034],"iteration":21,"passed_time":0.09346629699,"remaining_time":4.155001748},
{"learn":[123.5895696],"iteration":22,"passed_time":0.09522677676,"remaining_time":4.045067865},
{"learn":[122.8785576],"iteration":23,"passed_time":0.09700332949,"remaining_time":3.944802066},
{"learn":[122.0657134],"iteration":24,"passed_time":0.09878247994,"remaining_time":3.852516718},
{"learn":[121.4106421],"iteration":25,"passed_time":0.1005237483,"remaining_time":3.765774264},
{"learn":[120.6870207],"iteration":26,"passed_time":0.1023117537,"remaining_time":3.687012459},
{"learn":[119.9214],"iteration":27,"passed_time":0.1040742609,"remaining_time":3.612863627},
{"learn":[119.1677883],"iteration":28,"passed_time":0.105826439,"remaining_time":3.543361114},
{"learn":[118.68856],"iteration":29,"passed_time":0.1076050579,"remaining_time":3.479230206},
{"learn":[118.1675105],"iteration":30,"passed_time":0.1093527983,"remaining_time":3.418156826},
{"learn":[117.6133361],"iteration":31,"passed_time":0.1111214346,"remaining_time":3.361423398},
{"learn":[117.0288096],"iteration":32,"passed_time":0.1129087277,"remaining_time":3.308567868},
{"learn":[116.434135],"iteration":33,"passed_time":0.1146547845,"remaining_time":3.25754476},
{"learn":[115.9671012],"iteration":34,"passed_time":0.1164261196,"remaining_time":3.21003444},
{"learn":[115.5400591],"iteration":35,"passed_time":0.1182071828,"remaining_time":3.165325673},
{"learn":[115.0980065],"iteration":36,"passed_time":0.1199857102,"remaining_time":3.122871322},
{"learn":[114.6663858],"iteration":37,"passed_time":0.1217408573,"remaining_time":3.081965914},
{"learn":[114.2397007],"iteration":38,"passed_time":0.1234957186,"remaining_time":3.043061168},
{"learn":[113.8288034],"iteration":39,"passed_time":0.125264395,"remaining_time":3.006345479},
{"learn":[113.4899882],"iteration":40,"passed_time":0.1270002322,"remaining_time":2.970566407},
{"learn":[113.0983421],"iteration":41,"passed_time":0.1287737864,"remaining_time":2.937268746},
{"learn":[112.646028],"iteration":42,"passed_time":0.1305158395,"remaining_time":2.904736241},
{"learn":[112.2870919],"iteration":43,"passed_time":0.1322661475,"remaining_time":2.87378266},
{"learn":[111.935063],"iteration":44,"passed_time":0.1340327861,"remaining_time":2.844473572},
{"learn":[111.6605361],"iteration":45,"passed_time":0.1358109653,"remaining_time":2.816601325},
{"learn":[111.3514036],"iteration":46,"passed_time":0.1375667447,"remaining_time":2.789385269},
{"learn":[111.0880448],"iteration":47,"passed_time":0.139319074,"remaining_time":2.763161634},
{"learn":[110.7918196],"iteration":48,"passed_time":0.1410825741,"remaining_time":2.738153633},
{"learn":[110.5595518],"iteration":49,"passed_time":0.1428366001,"remaining_time":2.713895403},
{"learn":[110.3043974],"iteration":50,"passed_time":0.144730104,"remaining_time":2.693115072},
{"learn":[110.0272553],"iteration":51,"passed_time":0.1468273791,"remaining_time":2.676776066},
{"learn":[109.7661549],"iteration":52,"passed_time":0.1486032064,"remaining_time":2.655230877},
{"learn":[109.4218958],"iteration":53,"passed_time":0.1503846923,"remaining_time":2.634517017},
{"learn":[109.1847288],"iteration":54,"passed_time":0.1521541747,"remaining_time":2.614285366},
{"learn":[108.8575798],"iteration":55,"passed_time":0.1539230036,"remaining_time":2.594702061},
{"learn":[108.5770368],"iteration":56,"passed_time":0.1557092819,"remaining_time":2.576032505},
{"learn":[108.3389798],"iteration":57,"passed_time":0.1574548045,"remaining_time":2.557283204},
{"learn":[108.1421564],"iteration":58,"passed_time":0.1592154716,"remaining_time":2.539351844},
{"learn":[107.9492546],"iteration":59,"passed_time":0.1609435833,"remaining_time":2.521449471},
{"learn":[107.7376415],"iteration":60,"passed_time":0.1626994611,"remaining_time":2.504504819},
{"learn":[107.4956471],"iteration":61,"passed_time":0.1644533202,"remaining_time":2.488019586},
{"learn":[107.3278852],"iteration":62,"passed_time":0.1661823782,"remaining_time":2.471633149},
{"learn":[107.1270014],"iteration":63,"passed_time":0.1679339289,"remaining_time":2.456033711},
{"learn":[106.9034478],"iteration":64,"passed_time":0.1697280169,"remaining_time":2.441472243},
{"learn":[106.7397574],"iteration":65,"passed_time":0.1714816551,"remaining_time":2.426725241},
{"learn":[106.578037],"iteration":66,"passed_time":0.1732304548,"remaining_time":2.412298721},
{"learn":[106.4200294],"iteration":67,"passed_time":0.1751378425,"remaining_time":2.400418665},
{"learn":[106.1836066],"iteration":68,"passed_time":0.1769050758,"remaining_time":2.386936603},
{"learn":[106.0114609],"iteration":69,"passed_time":0.1787077037,"remaining_time":2.374259492},
{"learn":[105.8570572],"iteration":70,"passed_time":0.1804858041,"remaining_time":2.361567775},
{"learn":[105.6691194],"iteration":71,"passed_time":0.1822197277,"remaining_time":2.348609824},
{"learn":[105.546469],"iteration":72,"passed_time":0.1839291569,"remaining_time":2.335648335},
{"learn":[105.4152989],"iteration":73,"passed_time":0.1856688933,"remaining_time":2.323370205},
{"learn":[105.2643269],"iteration":74,"passed_time":0.187423006,"remaining_time":2.311550408},
{"learn":[105.1629915],"iteration":75,"passed_time":0.1891517046,"remaining_time":2.299686513},
{"learn":[105.0563048],"iteration":76,"passed_time":0.1908889012,"remaining_time":2.288187738},
{"learn":[104.9495334],"iteration":77,"passed_time":0.1926000179,"remaining_time":2.276630981},
{"learn":[104.8351121],"iteration":78,"passed_time":0.1943286494,"remaining_time":2.265527672},
{"learn":[104.7566227],"iteration":79,"passed_time":0.1960519412,"remaining_time":2.254597323},
{"learn":[104.667182],"iteration":80,"passed_time":0.1977674721,"remaining_time":2.243806257},
{"learn":[104.5663521],"iteration":81,"passed_time":0.1994297477,"remaining_time":2.232640346},
{"learn":[104.4075012],"iteration":82,"passed_time":0.2011568711,"remaining_time":2.222419889},
{"learn":[104.3013727],"iteration":83,"passed_time":0.2029259902,"remaining_time":2.212859607},
{"learn":[104.1693325],"iteration":84,"passed_time":0.2046745698,"remaining_time":2.203261546},
{"learn":[104.0157944],"iteration":85,"passed_time":0.2064027098,"remaining_time":2.193628799},
{"learn":[103.9520113],"iteration":86,"passed_time":0.2081173601,"remaining_time":2.184036204},
{"learn":[103.8547686],"iteration":87,"passed_time":0.2098615225,"remaining_time":2.174928506},
{"learn":[103.7270571],"iteration":88,"passed_time":0.2116045494,"remaining_time":2.165974657},
{"learn":[103.5764241],"iteration":89,"passed_time":0.2133698743,"remaining_time":2.157406506},
{"learn":[103.4980544],"iteration":90,"passed_time":0.2150664639,"remaining_time":2.148301271},
{"learn":[103.3508277],"iteration":91,"passed_time":0.2168125269,"remaining_time":2.139845374},
{"learn":[103.1923034],"iteration":92,"passed_time":0.2185537591,"remaining_time":2.131486661},
{"learn":[103.0976119],"iteration":93,"passed_time":0.2202878068,"remaining_time":2.1231995},
{"learn":[102.9525728],"iteration":94,"passed_time":0.2220470945,"remaining_time":2.115290742},
{"learn":[102.8517787],"iteration":95,"passed_time":0.223778538,"remaining_time":2.1072479},
{"learn":[102.7268296],"iteration":96,"passed_time":0.2254986517,"remaining_time":2.099229717},
{"learn":[102.6586992],"iteration":97,"passed_time":0.2272625632,"remaining_time":2.091743184},
{"learn":[102.5672571],"iteration":98,"passed_time":0.2290249631,"remaining_time":2.084358503},
{"learn":[102.3776054],"iteration":99,"passed_time":0.2307791233,"remaining_time":2.07701211},
{"learn":[102.2594632],"iteration":100,"passed_time":0.2325333846,"remaining_time":2.069777354},
{"learn":[102.1769746],"iteration":101,"passed_time":0.2342470058,"remaining_time":2.062292267},
{"learn":[102.121514],"iteration":102,"passed_time":0.2359695194,"remaining_time":2.054996689},
{"learn":[102.0322321],"iteration":103,"passed_time":0.2376818139,"remaining_time":2.047720243},
{"learn":[101.9588051],"iteration":104,"passed_time":0.2394230718,"remaining_time":2.04079666},
{"learn":[101.8894931],"iteration":105,"passed_time":0.2411583456,"remaining_time":2.033920387},
{"learn":[101.7992572],"iteration":106,"passed_time":0.242906849,"remaining_time":2.027250618},
{"learn":[101.7246087],"iteration":107,"passed_time":0.244654284,"remaining_time":2.020663161},
{"learn":[101.649284],"iteration":108,"passed_time":0.2463693945,"remaining_time":2.01390028},
{"learn":[101.5778573],"iteration":109,"passed_time":0.2480534313,"remaining_time":2.006977762},
{"learn":[101.4993585],"iteration":110,"passed_time":0.2498160377,"remaining_time":2.000778897},
{"learn":[101.4380149],"iteration":111,"passed_time":0.2515266033,"remaining_time":1.99424664},
{"learn":[101.3636366],"iteration":112,"passed_time":0.253250031,"remaining_time":1.987900686},
{"learn":[101.211648],"iteration":113,"passed_time":0.2550415836,"remaining_time":1.98216529},
{"learn":[101.1448684],"iteration":114,"passed_time":0.2567503997,"remaining_time":1.975861772},
{"learn":[101.0261153],"iteration":115,"passed_time":0.258498202,"remaining_time":1.969934574},
{"learn":[100.9729778],"iteration":116,"passed_time":0.2602218149,"remaining_time":1.963896261},
{"learn":[100.93109],"iteration":117,"passed_time":0.2619238876,"remaining_time":1.957770075},
{"learn":[100.8584894],"iteration":118,"passed_time":0.2636611953,"remaining_time":1.951979102},
{"learn":[100.7835391],"iteration":119,"passed_time":0.2653878621,"remaining_time":1.946177656},
{"learn":[100.6848689],"iteration":120,"passed_time":0.2671174169,"remaining_time":1.940464541},
{"learn":[100.5875871],"iteration":121,"passed_time":0.2688676761,"remaining_time":1.934965735},
{"learn":[100.540117],"iteration":122,"passed_time":0.2705431991,"remaining_time":1.928995005},
{"learn":[100.4432189],"iteration":123,"passed_time":0.2722849939,"remaining_time":1.923561731},
{"learn":[100.3823393],"iteration":124,"passed_time":0.2739982334,"remaining_time":1.917987633},
{"learn":[100.3009939],"iteration":125,"passed_time":0.2757543826,"remaining_time":1.912772463},
{"learn":[100.2124404],"iteration":126,"passed_time":0.2775042205,"remaining_time":1.907568382},
{"learn":[100.1632819],"iteration":127,"passed_time":0.2792007771,"remaining_time":1.902055294},
{"learn":[100.0939455],"iteration":128,"passed_time":0.2848635171,"remaining_time":1.923380802},
{"learn":[100.0097789],"iteration":129,"passed_time":0.2873947627,"remaining_time":1.923334181},
{"learn":[99.96520184],"iteration":130,"passed_time":0.2899659282,"remaining_time":1.92351444},
{"learn":[99.91954978],"iteration":131,"passed_time":0.2925453317,"remaining_time":1.923707182},
{"learn":[99.83569431],"iteration":132,"passed_time":0.2951821594,"remaining_time":1.924232573},
{"learn":[99.75905285],"iteration":133,"passed_time":0.2973838681,"remaining_time":1.92189873},
{"learn":[99.68662836],"iteration":134,"passed_time":0.2993122188,"remaining_time":1.917815328},
{"learn":[99.61243122],"iteration":135,"passed_time":0.3011801377,"remaining_time":1.913379698},
{"learn":[99.52285877],"iteration":136,"passed_time":0.303057413,"remaining_time":1.909040492},
{"learn":[99.46671717],"iteration":137,"passed_time":0.3047829182,"remaining_time":1.903788953},
{"learn":[99.39423954],"iteration":138,"passed_time":0.3065203009,"remaining_time":1.89866172},
{"learn":[99.34354586],"iteration":139,"passed_time":0.3082217178,"remaining_time":1.893361981},
{"learn":[99.29922775],"iteration":140,"passed_time":0.3099063999,"remaining_time":1.88801133},
{"learn":[99.2527476],"iteration":141,"passed_time":0.3116272377,"remaining_time":1.882930774},
{"learn":[99.20530369],"iteration":142,"passed_time":0.3133532322,"remaining_time":1.877928112},
{"learn":[99.14455758],"iteration":143,"passed_time":0.3150587213,"remaining_time":1.872849065},
{"learn":[99.11285786],"iteration":144,"passed_time":0.3167440395,"remaining_time":1.867697612},
{"learn":[99.05127735],"iteration":145,"passed_time":0.3184569392,"remaining_time":1.862754973},
{"learn":[98.98894074],"iteration":146,"passed_time":0.3201684694,"remaining_time":1.857848329},
{"learn":[98.86941612],"iteration":147,"passed_time":0.3219070869,"remaining_time":1.853140797},
{"learn":[98.75406487],"iteration":148,"passed_time":0.3236514793,"remaining_time":1.8485061},
{"learn":[98.7014055],"iteration":149,"passed_time":0.3253717211,"remaining_time":1.843773086},
{"learn":[98.67023346],"iteration":150,"passed_time":0.3270442961,"remaining_time":1.838811969},
{"learn":[98.63595016],"iteration":151,"passed_time":0.3287367739,"remaining_time":1.83400516},
{"learn":[98.57607558],"iteration":152,"passed_time":0.3304803851,"remaining_time":1.829522132},
{"learn":[98.52358659],"iteration":153,"passed_time":0.3321836682,"remaining_time":1.824853138},
{"learn":[98.48345192],"iteration":154,"passed_time":0.3338855726,"remaining_time":1.820214896},
{"learn":[98.38582902],"iteration":155,"passed_time":0.3356279647,"remaining_time":1.815833348},
{"learn":[98.34927151],"iteration":156,"passed_time":0.3375951987,"remaining_time":1.812692691},
{"learn":[98.29170546],"iteration":157,"passed_time":0.3393689664,"remaining_time":1.808535884},
{"learn":[98.18720845],"iteration":158,"passed_time":0.3412748501,"remaining_time":1.805107855},
{"learn":[98.10477683],"iteration":159,"passed_time":0.3430841265,"remaining_time":1.801191664},
{"learn":[98.05651625],"iteration":160,"passed_time":0.3448197272,"remaining_time":1.796917709},
{"learn":[97.96344182],"iteration":161,"passed_time":0.3466101856,"remaining_time":1.792958861},
{"learn":[97.8939847],"iteration":162,"passed_time":0.348334199,"remaining_time":1.788685427},
{"learn":[97.8104816],"iteration":163,"passed_time":0.3500972181,"remaining_time":1.784641916},
{"learn":[97.78377304],"iteration":164,"passed_time":0.3517775025,"remaining_time":1.780207361},
{"learn":[97.73088744],"iteration":165,"passed_time":0.3534660093,"remaining_time":1.7758473},
{"learn":[97.69570015],"iteration":166,"passed_time":0.3552110832,"remaining_time":1.771801391},
{"learn":[97.65479527],"iteration":167,"passed_time":0.3569086427,"remaining_time":1.767547564},
{"learn":[97.60481802],"iteration":168,"passed_time":0.3586425157,"remaining_time":1.763502548},
{"learn":[97.55784475],"iteration":169,"passed_time":0.3603508831,"remaining_time":1.759360194},
{"learn":[97.4927574],"iteration":170,"passed_time":0.3620859073,"remaining_time":1.755375539},
{"learn":[97.47993601],"iteration":171,"passed_time":0.3637714299,"remaining_time":1.751178744},
{"learn":[97.4298912],"iteration":172,"passed_time":0.3655124564,"remaining_time":1.747276309},
{"learn":[97.35533309],"iteration":173,"passed_time":0.3672726892,"remaining_time":1.743489892},
{"learn":[97.23603516],"iteration":174,"passed_time":0.3690265222,"remaining_time":1.739696462},
{"learn":[97.20215995],"iteration":175,"passed_time":0.3707050415,"remaining_time":1.735573604},
{"learn":[97.14021292],"iteration":176,"passed_time":0.3724381896,"remaining_time":1.731732373},
{"learn":[97.10187183],"iteration":177,"passed_time":0.3742161788,"remaining_time":1.728121905},
{"learn":[97.07812156],"iteration":178,"passed_time":0.3758851178,"remaining_time":1.724031741},
{"learn":[96.93369669],"iteration":179,"passed_time":0.3776399429,"remaining_time":1.72035974},
{"learn":[96.81756761],"iteration":180,"passed_time":0.3794366835,"remaining_time":1.716898584},
{"learn":[96.75848271],"iteration":181,"passed_time":0.3811724353,"remaining_time":1.713181605},
{"learn":[96.71744673],"iteration":182,"passed_time":0.3828804833,"remaining_time":1.709362595},
{"learn":[96.63449099],"iteration":183,"passed_time":0.3846476264,"remaining_time":1.705828604},
{"learn":[96.58367599],"iteration":184,"passed_time":0.386349469,"remaining_time":1.702026039},
{"learn":[96.54668155],"iteration":185,"passed_time":0.388051671,"remaining_time":1.698247636},
{"learn":[96.46893052],"iteration":186,"passed_time":0.3897769466,"remaining_time":1.694591752},
{"learn":[96.41165451],"iteration":187,"passed_time":0.3915193426,"remaining_time":1.691030352},
{"learn":[96.31700487],"iteration":188,"passed_time":0.3932983223,"remaining_time":1.687645182},
{"learn":[96.27035796],"iteration":189,"passed_time":0.3950210429,"remaining_time":1.684037077},
{"learn":[96.24846302],"iteration":190,"passed_time":0.39672137,"remaining_time":1.680353866},
{"learn":[96.19701834],"iteration":191,"passed_time":0.3984737887,"remaining_time":1.676910527},
{"learn":[96.16609457],"iteration":192,"passed_time":0.4001155907,"remaining_time":1.673022185},
{"learn":[96.08809978],"iteration":193,"passed_time":0.4018538657,"remaining_time":1.669557813},
{"learn":[96.03616454],"iteration":194,"passed_time":0.4035710275,"remaining_time":1.666023985},
{"learn":[95.99577257],"iteration":195,"passed_time":0.4052576067,"remaining_time":1.662383244},
{"learn":[95.95727913],"iteration":196,"passed_time":0.4069505581,"remaining_time":1.658788316},
{"learn":[95.90784912],"iteration":197,"passed_time":0.4086590096,"remaining_time":1.655275382},
{"learn":[95.80314683],"iteration":198,"passed_time":0.4104273723,"remaining_time":1.652021735},
{"learn":[95.7760953],"iteration":199,"passed_time":0.4120960938,"remaining_time":1.648384375},
{"learn":[95.735727],"iteration":200,"passed_time":0.4138282201,"remaining_time":1.645018646},
{"learn":[95.71184036],"iteration":201,"passed_time":0.4154699824,"remaining_time":1.641312109},
{"learn":[95.63319013],"iteration":202,"passed_time":0.4173296371,"remaining_time":1.638481383},
{"learn":[95.60892732],"iteration":203,"passed_time":0.41911893,"remaining_time":1.635385629},
{"learn":[95.59050602],"iteration":204,"passed_time":0.4208082995,"remaining_time":1.631915113},
{"learn":[95.56846137],"iteration":205,"passed_time":0.4224839014,"remaining_time":1.628408824},
{"learn":[95.54776835],"iteration":206,"passed_time":0.4241559561,"remaining_time":1.624906634},
{"learn":[95.44204368],"iteration":207,"passed_time":0.4259134399,"remaining_time":1.621747329},
{"learn":[95.39590386],"iteration":208,"passed_time":0.4277221573,"remaining_time":1.618795342},
{"learn":[95.36732954],"iteration":209,"passed_time":0.429378875,"remaining_time":1.615282435},
{"learn":[95.34363596],"iteration":210,"passed_time":0.431059088,"remaining_time":1.611874978},
{"learn":[95.30537791],"iteration":211,"passed_time":0.4327986845,"remaining_time":1.608704544},
{"learn":[95.2569667],"iteration":212,"passed_time":0.4345508523,"remaining_time":1.605593994},
{"learn":[95.24038927],"iteration":213,"passed_time":0.4362743214,"remaining_time":1.602390732},
{"learn":[95.10751703],"iteration":214,"passed_time":0.4380561419,"remaining_time":1.599414285},
{"learn":[95.06686403],"iteration":215,"passed_time":0.4399138472,"remaining_time":1.596724334},
{"learn":[95.02235294],"iteration":216,"passed_time":0.4416349861,"remaining_time":1.593549282},
{"learn":[94.94120999],"iteration":217,"passed_time":0.4433719797,"remaining_time":1.590444441},
{"learn":[94.91843182],"iteration":218,"passed_time":0.4450499763,"remaining_time":1.587141696},
{"learn":[94.88983985],"iteration":219,"passed_time":0.4467231033,"remaining_time":1.583836457},
{"learn":[94.87333877],"iteration":220,"passed_time":0.4483868385,"remaining_time":1.580512883},
{"learn":[94.82688666],"iteration":221,"passed_time":0.4502137556,"remaining_time":1.577776135},
{"learn":[94.78169757],"iteration":222,"passed_time":0.4518988281,"remaining_time":1.574553316},
{"learn":[94.72270631],"iteration":223,"passed_time":0.453620743,"remaining_time":1.57147186},
{"learn":[94.64463646],"iteration":224,"passed_time":0.4553979228,"remaining_time":1.568592845},
{"learn":[94.60299764],"iteration":225,"passed_time":0.4571269045,"remaining_time":1.565558514},
{"learn":[94.53741425],"iteration":226,"passed_time":0.4588778087,"remaining_time":1.562610335},
{"learn":[94.46715321],"iteration":227,"passed_time":0.4606316909,"remaining_time":1.559682743},
{"learn":[94.44842812],"iteration":228,"passed_time":0.4623048179,"remaining_time":1.556493514},
{"learn":[94.43222019],"iteration":229,"passed_time":0.4639705444,"remaining_time":1.553292692},
{"learn":[94.37405092],"iteration":230,"passed_time":0.465708805,"remaining_time":1.550346628},
{"learn":[94.35788203],"iteration":231,"passed_time":0.4673588968,"remaining_time":1.547119107},
{"learn":[94.32934735],"iteration":232,"passed_time":0.469005428,"remaining_time":1.543893405},
{"learn":[94.31574166],"iteration":233,"passed_time":0.4706537809,"remaining_time":1.540687163},
{"learn":[94.29260484],"iteration":234,"passed_time":0.4723518734,"remaining_time":1.537656098},
{"learn":[94.21100731],"iteration":235,"passed_time":0.4741144001,"remaining_time":1.534844922},
{"learn":[94.15401975],"iteration":236,"passed_time":0.4758576845,"remaining_time":1.531980647},
{"learn":[94.10808397],"iteration":237,"passed_time":0.4775643927,"remaining_time":1.529008686},
{"learn":[94.01693745],"iteration":238,"passed_time":0.4793343867,"remaining_time":1.526248821},
{"learn":[94.00423865],"iteration":239,"passed_time":0.4810201171,"remaining_time":1.523230371},
{"learn":[93.95975056],"iteration":240,"passed_time":0.4827559717,"remaining_time":1.52038084},
{"learn":[93.91215516],"iteration":241,"passed_time":0.4844758785,"remaining_time":1.517490562},
{"learn":[93.84697581],"iteration":242,"passed_time":0.4862253361,"remaining_time":1.514701973},
{"learn":[93.77337071],"iteration":243,"passed_time":0.4881199235,"remaining_time":1.512371566},
{"learn":[93.74353529],"iteration":244,"passed_time":0.4898187065,"remaining_time":1.50944132},
{"learn":[93.72603347],"iteration":245,"passed_time":0.4915000846,"remaining_time":1.506467739},
{"learn":[93.66113891],"iteration":246,"passed_time":0.4932148447,"remaining_time":1.503606389},
{"learn":[93.60497117],"iteration":247,"passed_time":0.4949309368,"remaining_time":1.500758325},
{"learn":[93.53513982],"iteration":248,"passed_time":0.4966863114,"remaining_time":1.498037831},
{"learn":[93.45877621],"iteration":249,"passed_time":0.4984588307,"remaining_time":1.495376492},
{"learn":[93.39200609],"iteration":250,"passed_time":0.5001763763,"remaining_time":1.492558191},
{"learn":[93.35570112],"iteration":251,"passed_time":0.5019705253,"remaining_time":1.489976004},
{"learn":[93.29897927],"iteration":252,"passed_time":0.5036694957,"remaining_time":1.487119025},
{"learn":[93.26900216],"iteration":253,"passed_time":0.5053437917,"remaining_time":1.484198695},
{"learn":[93.24327615],"iteration":254,"passed_time":0.5070215843,"remaining_time":1.481298354},
{"learn":[93.20542666],"iteration":255,"passed_time":0.508737815,"remaining_time":1.478519275},
{"learn":[93.14411586],"iteration":256,"passed_time":0.5105101003,"remaining_time":1.475910524},
{"learn":[93.13070712],"iteration":257,"passed_time":0.5121751549,"remaining_time":1.472999864},
{"learn":[93.06093198],"iteration":258,"passed_time":0.513923904,"remaining_time":1.470338274},
{"learn":[93.03018945],"iteration":259,"passed_time":0.5156075979,"remaining_time":1.467498548},
{"learn":[92.99160827],"iteration":260,"passed_time":0.5173177482,"remaining_time":1.46474259},
{"learn":[92.88248289],"iteration":261,"passed_time":0.5191235673,"remaining_time":1.462264094},
{"learn":[92.82294874],"iteration":262,"passed_time":0.5208766922,"remaining_time":1.45964305},
{"learn":[92.79799391],"iteration":263,"passed_time":0.5225578804,"remaining_time":1.45682803},
{"learn":[92.77551527],"iteration":264,"passed_time":0.5242511952,"remaining_time":1.454055202},
{"learn":[92.73212307],"iteration":265,"passed_time":0.5259540421,"remaining_time":1.451316793},
{"learn":[92.71726355],"iteration":266,"passed_time":0.5276461801,"remaining_time":1.448556742},
{"learn":[92.65526658],"iteration":267,"passed_time":0.5293974398,"remaining_time":1.445966141},
{"learn":[92.61754973],"iteration":268,"passed_time":0.5310939288,"remaining_time":1.443232944},
{"learn":[92.57825729],"iteration":269,"passed_time":0.5328167892,"remaining_time":1.440578726},
{"learn":[92.55656317],"iteration":270,"passed_time":0.5344635104,"remaining_time":1.437726565},
{"learn":[92.51947711],"iteration":271,"passed_time":0.5361945787,"remaining_time":1.43510902},
{"learn":[92.39946716],"iteration":272,"passed_time":0.5385688972,"remaining_time":1.434210946},
{"learn":[92.27999028],"iteration":273,"passed_time":0.5403644295,"remaining_time":1.431768525},
{"learn":[92.24164412],"iteration":274,"passed_time":0.5420818135,"remaining_time":1.429124781},
{"learn":[92.22639231],"iteration":275,"passed_time":0.54375144,"remaining_time":1.426362473},
{"learn":[92.18231171],"iteration":276,"passed_time":0.5454717903,"remaining_time":1.423740449},
{"learn":[92.13471342],"iteration":277,"passed_time":0.5471839784,"remaining_time":1.421103714},
{"learn":[92.12623861],"iteration":278,"passed_time":0.5488406591,"remaining_time":1.418330162},
{"learn":[92.07130217],"iteration":279,"passed_time":0.5507423133,"remaining_time":1.41619452},
{"learn":[92.00317429],"iteration":280,"passed_time":0.5524997671,"remaining_time":1.413691575},
{"learn":[91.98548667],"iteration":281,"passed_time":0.5541795988,"remaining_time":1.410996284},
{"learn":[91.9544294],"iteration":282,"passed_time":0.5559041463,"remaining_time":1.408421459},
{"learn":[91.93428684],"iteration":283,"passed_time":0.5576747703,"remaining_time":1.405968787},
{"learn":[91.87613771],"iteration":284,"passed_time":0.5593946292,"remaining_time":1.403393543},
{"learn":[91.82028606],"iteration":285,"passed_time":0.5610991997,"remaining_time":1.400786114},
{"learn":[91.79510102],"iteration":286,"passed_time":0.5628000916,"remaining_time":1.398175837},
{"learn":[91.75061537],"iteration":287,"passed_time":0.5645235206,"remaining_time":1.395627593},
{"learn":[91.6766763],"iteration":288,"passed_time":0.5662943682,"remaining_time":1.393201715},
{"learn":[91.66323769],"iteration":289,"passed_time":0.567955114,"remaining_time":1.390510796},
{"learn":[91.58859284],"iteration":290,"passed_time":0.5697202102,"remaining_time":1.388081199},
{"learn":[91.57318695],"iteration":291,"passed_time":0.5713960939,"remaining_time":1.385439844},
{"learn":[91.5481683],"iteration":292,"passed_time":0.5730846499,"remaining_time":1.382835657},
{"learn":[91.52218216],"iteration":293,"passed_time":0.5747518587,"remaining_time":1.380186436},
{"learn":[91.48096158],"iteration":294,"passed_time":0.576587442,"remaining_time":1.37794626},
{"learn":[91.45114147],"iteration":295,"passed_time":0.5783163397,"remaining_time":1.375455078},
{"learn":[91.42318078],"iteration":296,"passed_time":0.5800362992,"remaining_time":1.372947873},
{"learn":[91.37807554],"iteration":297,"passed_time":0.581789032,"remaining_time":1.370523156},
{"learn":[91.36283047],"iteration":298,"passed_time":0.5835463942,"remaining_time":1.368113787},
{"learn":[91.34993078],"iteration":299,"passed_time":0.5852456801,"remaining_time":1.365573254},
{"learn":[91.30916143],"iteration":300,"passed_time":0.5871064707,"remaining_time":1.363413365},
{"learn":[91.21937292],"iteration":301,"passed_time":0.588920146,"remaining_time":1.361146563},
{"learn":[91.18283225],"iteration":302,"passed_time":0.5906643276,"remaining_time":1.358722892},
{"learn":[91.16208289],"iteration":303,"passed_time":0.5923463601,"remaining_time":1.356161403},
{"learn":[91.12558269],"iteration":304,"passed_time":0.5940602349,"remaining_time":1.35367824},
{"learn":[91.03518351],"iteration":305,"passed_time":0.5958162586,"remaining_time":1.351295698},
{"learn":[91.02170681],"iteration":306,"passed_time":0.5974870916,"remaining_time":1.348724933},
{"learn":[91.00792528],"iteration":307,"passed_time":0.5991828891,"remaining_time":1.346216102},
{"learn":[90.96301467],"iteration":308,"passed_time":0.6009281661,"remaining_time":1.34382318},
{"learn":[90.94173156],"iteration":309,"passed_time":0.6026028538,"remaining_time":1.34127732},
{"learn":[90.87001121],"iteration":310,"passed_time":0.6043517724,"remaining_time":1.338901515},
{"learn":[90.81757384],"iteration":311,"passed_time":0.6060682266,"remaining_time":1.336458141},
{"learn":[90.78554172],"iteration":312,"passed_time":0.6077494378,"remaining_time":1.333942057},
{"learn":[90.68290522],"iteration":313,"passed_time":0.6094935021,"remaining_time":1.331568607},
{"learn":[90.64686552],"iteration":314,"passed_time":0.6112259813,"remaining_time":1.329173959},
{"learn":[90.59319807],"iteration":315,"passed_time":0.612962354,"remaining_time":1.326791931},
{"learn":[90.57889802],"iteration":316,"passed_time":0.6146394469,"remaining_time":1.324286253},
{"learn":[90.57255705],"iteration":317,"passed_time":0.6162580743,"remaining_time":1.321660398},
{"learn":[90.53634222],"iteration":318,"passed_time":0.6179567963,"remaining_time":1.319211844},
{"learn":[90.45562405],"iteration":319,"passed_time":0.6197023643,"remaining_time":1.316867524},
{"learn":[90.38698754],"iteration":320,"passed_time":0.6214736283,"remaining_time":1.314581289},
{"learn":[90.33150899],"iteration":321,"passed_time":0.6232231609,"remaining_time":1.312252494},
{"learn":[90.29628531],"iteration":322,"passed_time":0.6249625217,"remaining_time":1.309905967},
{"learn":[90.2745596],"iteration":323,"passed_time":0.6266538331,"remaining_time":1.307462936},
{"learn":[90.25111198],"iteration":324,"passed_time":0.6283514859,"remaining_time":1.305037702},
{"learn":[90.24512058],"iteration":325,"passed_time":0.6300027006,"remaining_time":1.302520921},
{"learn":[90.17864072],"iteration":326,"passed_time":0.6317598519,"remaining_time":1.300227463},
{"learn":[90.14823944],"iteration":327,"passed_time":0.6334815638,"remaining_time":1.297864667},
{"learn":[90.12625429],"iteration":328,"passed_time":0.6351681944,"remaining_time":1.29543422},
{"learn":[90.11015676],"iteration":329,"passed_time":0.636939699,"remaining_time":1.293180601},
{"learn":[90.06701365],"iteration":330,"passed_time":0.6386764146,"remaining_time":1.290859581},
{"learn":[90.02169672],"iteration":331,"passed_time":0.6404149145,"remaining_time":1.288545671},
{"learn":[89.99285635],"iteration":332,"passed_time":0.6421076716,"remaining_time":1.286143595},
{"learn":[89.97917244],"iteration":333,"passed_time":0.6438167178,"remaining_time":1.283778246},
{"learn":[89.96304678],"iteration":334,"passed_time":0.6454795455,"remaining_time":1.281325068},
{"learn":[89.95729664],"iteration":335,"passed_time":0.6471353879,"remaining_time":1.27886279},
{"learn":[89.94722521],"iteration":336,"passed_time":0.6488040083,"remaining_time":1.276430438},
{"learn":[89.9269382],"iteration":337,"passed_time":0.6505025186,"remaining_time":1.274061146},
{"learn":[89.90773105],"iteration":338,"passed_time":0.6522154117,"remaining_time":1.271723856},
{"learn":[89.88054906],"iteration":339,"passed_time":0.6540465399,"remaining_time":1.269619754},
{"learn":[89.8432865],"iteration":340,"passed_time":0.6557867016,"remaining_time":1.267341456},
{"learn":[89.82632531],"iteration":341,"passed_time":0.657486678,"remaining_time":1.264988989},
{"learn":[89.79300499],"iteration":342,"passed_time":0.6592075237,"remaining_time":1.262680301},
{"learn":[89.77597384],"iteration":343,"passed_time":0.6609057983,"remaining_time":1.260331987},
{"learn":[89.74215911],"iteration":344,"passed_time":0.6626600752,"remaining_time":1.258093766},
{"learn":[89.67713222],"iteration":345,"passed_time":0.6644625232,"remaining_time":1.255949394},
{"learn":[89.6380739],"iteration":346,"passed_time":0.6661982506,"remaining_time":1.253681434},
{"learn":[89.58383757],"iteration":347,"passed_time":0.6679123437,"remaining_time":1.251376},
{"learn":[89.52950622],"iteration":348,"passed_time":0.669697561,"remaining_time":1.249206625},
{"learn":[89.52384565],"iteration":349,"passed_time":0.6713324103,"remaining_time":1.246760191},
{"learn":[89.4598318],"iteration":350,"passed_time":0.6730995726,"remaining_time":1.244563027},
{"learn":[89.42882239],"iteration":351,"passed_time":0.6748134055,"remaining_time":1.242270133},
{"learn":[89.41698035],"iteration":352,"passed_time":0.6764899938,"remaining_time":1.239912255},
{"learn":[89.40647866],"iteration":353,"passed_time":0.6781616207,"remaining_time":1.237549172},
{"learn":[89.39839882],"iteration":354,"passed_time":0.679848995,"remaining_time":1.235218597},
{"learn":[89.38052463],"iteration":355,"passed_time":0.6815302581,"remaining_time":1.232880579},
{"learn":[89.31719422],"iteration":356,"passed_time":0.6832721783,"remaining_time":1.230655492},
{"learn":[89.31175091],"iteration":357,"passed_time":0.6849442914,"remaining_time":1.228307919},
{"learn":[89.27960612],"iteration":358,"passed_time":0.686684396,"remaining_time":1.226085509},
{"learn":[89.27359139],"iteration":359,"passed_time":0.6883430548,"remaining_time":1.223720986},
{"learn":[89.20442416],"iteration":360,"passed_time":0.6900928418,"remaining_time":1.221521678},
{"learn":[89.19199057],"iteration":361,"passed_time":0.691773677,"remaining_time":1.219203331},
{"learn":[89.14056112],"iteration":362,"passed_time":0.6935061444,"remaining_time":1.216979102},
{"learn":[89.09613388],"iteration":363,"passed_time":0.6952663693,"remaining_time":1.214806074},
{"learn":[89.05266239],"iteration":364,"passed_time":0.6970060913,"remaining_time":1.212599638},
{"learn":[89.00554672],"iteration":365,"passed_time":0.698750811,"remaining_time":1.21040441},
{"learn":[88.97498005],"iteration":366,"passed_time":0.7004544844,"remaining_time":1.208140841},
{"learn":[88.91762892],"iteration":367,"passed_time":0.7022179654,"remaining_time":1.205983027},
{"learn":[88.89133691],"iteration":368,"passed_time":0.7039402629,"remaining_time":1.203756926},
{"learn":[88.84228182],"iteration":369,"passed_time":0.7056807492,"remaining_time":1.201564519},
{"learn":[88.78778954],"iteration":370,"passed_time":0.7075616404,"remaining_time":1.199612593},
{"learn":[88.78128101],"iteration":371,"passed_time":0.7092424421,"remaining_time":1.197323262},
{"learn":[88.77616374],"iteration":372,"passed_time":0.7108780155,"remaining_time":1.194961168},
{"learn":[88.74336516],"iteration":373,"passed_time":0.7125796734,"remaining_time":1.192713571},
{"learn":[88.73002267],"iteration":374,"passed_time":0.7142460194,"remaining_time":1.190410032},
{"learn":[88.66056522],"iteration":375,"passed_time":0.715966639,"remaining_time":1.188199954},
{"learn":[88.62644803],"iteration":376,"passed_time":0.7176892454,"remaining_time":1.185995756},
{"learn":[88.5953203],"iteration":377,"passed_time":0.7194175871,"remaining_time":1.183803543},
{"learn":[88.52754768],"iteration":378,"passed_time":0.7211853171,"remaining_time":1.181678316},
{"learn":[88.48249227],"iteration":379,"passed_time":0.7228971628,"remaining_time":1.179463792},
{"learn":[88.44797194],"iteration":380,"passed_time":0.7246236266,"remaining_time":1.177275656},
{"learn":[88.4027426],"iteration":381,"passed_time":0.7263569824,"remaining_time":1.175101087},
{"learn":[88.39773415],"iteration":382,"passed_time":0.7279903573,"remaining_time":1.172767756},
{"learn":[88.3922141],"iteration":383,"passed_time":0.7296297829,"remaining_time":1.170447777},
{"learn":[88.3654791],"iteration":384,"passed_time":0.731345756,"remaining_time":1.16825361},
{"learn":[88.29987396],"iteration":385,"passed_time":0.7341399544,"remaining_time":1.167777026},
{"learn":[88.28167286],"iteration":386,"passed_time":0.7358593945,"remaining_time":1.165586069},
{"learn":[88.25632468],"iteration":387,"passed_time":0.7375882713,"remaining_time":1.163412428},
{"learn":[88.24777665],"iteration":388,"passed_time":0.7392419399,"remaining_time":1.161122944},
{"learn":[88.23758855],"iteration":389,"passed_time":0.7409366329,"remaining_time":1.158900887},
{"learn":[88.20688985],"iteration":390,"passed_time":0.7426485922,"remaining_time":1.156708421},
{"learn":[88.20157212],"iteration":391,"passed_time":0.7442928904,"remaining_time":1.154413463},
{"learn":[88.13395631],"iteration":392,"passed_time":0.7460157879,"remaining_time":1.152243214},
{"learn":[88.1266714],"iteration":393,"passed_time":0.7477839614,"remaining_time":1.150144875},
{"learn":[88.04690038],"iteration":394,"passed_time":0.7495320626,"remaining_time":1.148017463},
{"learn":[88.0374696],"iteration":395,"passed_time":0.7512252015,"remaining_time":1.145808136},
{"learn":[88.03241813],"iteration":396,"passed_time":0.7528743417,"remaining_time":1.143534579},
{"learn":[88.026539],"iteration":397,"passed_time":0.7545198834,"remaining_time":1.141258718},
{"learn":[87.97168808],"iteration":398,"passed_time":0.7562922711,"remaining_time":1.13917708},
{"learn":[87.93898904],"iteration":399,"passed_time":0.7580148806,"remaining_time":1.137022321},
{"learn":[87.85905594],"iteration":400,"passed_time":0.7597922412,"remaining_time":1.134951502},
{"learn":[87.84933022],"iteration":401,"passed_time":0.7615075651,"remaining_time":1.132789861},
{"learn":[87.84455555],"iteration":402,"passed_time":0.7631468225,"remaining_time":1.130517749},
{"learn":[87.839836],"iteration":403,"passed_time":0.7647707298,"remaining_time":1.128226126},
{"learn":[87.82826895],"iteration":404,"passed_time":0.7664867792,"remaining_time":1.126073169},
{"learn":[87.82024931],"iteration":405,"passed_time":0.7681720264,"remaining_time":1.1238773},
{"learn":[87.80461887],"iteration":406,"passed_time":0.7699315337,"remaining_time":1.121792136},
{"learn":[87.79549165],"iteration":407,"passed_time":0.7715889986,"remaining_time":1.119560508},
{"learn":[87.79095735],"iteration":408,"passed_time":0.7733126137,"remaining_time":1.117427273},
{"learn":[87.7627322],"iteration":409,"passed_time":0.7750133609,"remaining_time":1.115263129},
{"learn":[87.75833371],"iteration":410,"passed_time":0.7766387631,"remaining_time":1.112993264},
{"learn":[87.74677832],"iteration":411,"passed_time":0.7782937367,"remaining_time":1.110768731},
{"learn":[87.73851232],"iteration":412,"passed_time":0.7799670654,"remaining_time":1.108573045},
{"learn":[87.73421797],"iteration":413,"passed_time":0.7816063124,"remaining_time":1.10633164},
{"learn":[87.68533486],"iteration":414,"passed_time":0.783374743,"remaining_time":1.10427524},
{"learn":[87.65421394],"iteration":415,"passed_time":0.7850768998,"remaining_time":1.102127186},
{"learn":[87.64722081],"iteration":416,"passed_time":0.7867274678,"remaining_time":1.099909146},
{"learn":[87.62219648],"iteration":417,"passed_time":0.7884379493,"remaining_time":1.09777724},
{"learn":[87.5623396],"iteration":418,"passed_time":0.7901953838,"remaining_time":1.095712453},
{"learn":[87.5152651],"iteration":419,"passed_time":0.7919660723,"remaining_time":1.093667433},
{"learn":[87.50757521],"iteration":420,"passed_time":0.7936422123,"remaining_time":1.091493684},
{"learn":[87.43525724],"iteration":421,"passed_time":0.7954253996,"remaining_time":1.089468912},
{"learn":[87.38309797],"iteration":422,"passed_time":0.7972061705,"remaining_time":1.087441987},
{"learn":[87.35665457],"iteration":423,"passed_time":0.7989457696,"remaining_time":1.085360291},
{"learn":[87.31000524],"iteration":424,"passed_time":0.800674791,"remaining_time":1.083265894},
{"learn":[87.28805122],"iteration":425,"passed_time":0.8023775983,"remaining_time":1.081137891},
{"learn":[87.27023785],"iteration":426,"passed_time":0.8040798753,"remaining_time":1.079011168},
{"learn":[87.23162393],"iteration":427,"passed_time":0.8058048921,"remaining_time":1.076916818},
{"learn":[87.19934644],"iteration":428,"passed_time":0.8075283316,"remaining_time":1.074822092},
{"learn":[87.13273299],"iteration":429,"passed_time":0.809291206,"remaining_time":1.072781366},
{"learn":[87.10859865],"iteration":430,"passed_time":0.8109879512,"remaining_time":1.070654627},
{"learn":[87.05020539],"iteration":431,"passed_time":0.8127421158,"remaining_time":1.068605374},
{"learn":[86.99359657],"iteration":432,"passed_time":0.8144940896,"remaining_time":1.066554616},
{"learn":[86.98490413],"iteration":433,"passed_time":0.8161753722,"remaining_time":1.064413043},
{"learn":[86.93984675],"iteration":434,"passed_time":0.8179145523,"remaining_time":1.062348786},
{"learn":[86.89294521],"iteration":435,"passed_time":0.8196423907,"remaining_time":1.060271349},
{"learn":[86.82496976],"iteration":436,"passed_time":0.8214052651,"remaining_time":1.058240651},
{"learn":[86.72773319],"iteration":437,"passed_time":0.823181831,"remaining_time":1.056228742},
{"learn":[86.67116946],"iteration":438,"passed_time":0.8249438301,"remaining_time":1.054199291},
{"learn":[86.66711689],"iteration":439,"passed_time":0.8265747161,"remaining_time":1.052004184},
{"learn":[86.63897519],"iteration":440,"passed_time":0.8283822109,"remaining_time":1.050035501},
{"learn":[86.57987581],"iteration":441,"passed_time":0.8301264391,"remaining_time":1.047987677},
{"learn":[86.55168617],"iteration":442,"passed_time":0.831869832,"remaining_time":1.045940173},
{"learn":[86.51963492],"iteration":443,"passed_time":0.833588107,"remaining_time":1.043862584},
{"learn":[86.51246105],"iteration":444,"passed_time":0.8352506436,"remaining_time":1.041717095},
{"learn":[86.50282092],"iteration":445,"passed_time":0.8368925829,"remaining_time":1.039548186},
{"learn":[86.47525512],"iteration":446,"passed_time":0.8385952516,"remaining_time":1.037456765},
{"learn":[86.44501128],"iteration":447,"passed_time":0.840330135,"remaining_time":1.035406774},
{"learn":[86.42158077],"iteration":448,"passed_time":0.8420392021,"remaining_time":1.033326504},
{"learn":[86.38497549],"iteration":449,"passed_time":0.8438107067,"remaining_time":1.031324197},
{"learn":[86.37047351],"iteration":450,"passed_time":0.8454796182,"remaining_time":1.029198028},
{"learn":[86.34354043],"iteration":451,"passed_time":0.8472045134,"remaining_time":1.027141755},
{"learn":[86.30697672],"iteration":452,"passed_time":0.8491247621,"remaining_time":1.025322836},
{"learn":[86.26849693],"iteration":453,"passed_time":0.8510700075,"remaining_time":1.023533533},
{"learn":[86.24731658],"iteration":454,"passed_time":0.852773403,"remaining_time":1.021453856},
{"learn":[86.20638334],"iteration":455,"passed_time":0.8545183008,"remaining_time":1.019425341},
{"learn":[86.19984267],"iteration":456,"passed_time":0.8561714148,"remaining_time":1.017289011},
{"learn":[86.15671166],"iteration":457,"passed_time":0.8580095501,"remaining_time":1.015373747},
{"learn":[86.13434564],"iteration":458,"passed_time":0.859778758,"remaining_time":1.013377578},
{"learn":[86.13042539],"iteration":459,"passed_time":0.8614444135,"remaining_time":1.011260833},
{"learn":[86.1157462],"iteration":460,"passed_time":0.8631113312,"remaining_time":1.009147522},
{"learn":[86.08738635],"iteration":461,"passed_time":0.8648346064,"remaining_time":1.007101771},
{"learn":[86.07674746],"iteration":462,"passed_time":0.8665380136,"remaining_time":1.00503437},
{"learn":[86.05136908],"iteration":463,"passed_time":0.8682315943,"remaining_time":1.002957186},
{"learn":[86.04404332],"iteration":464,"passed_time":0.8698507972,"remaining_time":1.000796078},
{"learn":[86.03531627],"iteration":465,"passed_time":0.8715117526,"remaining_time":0.9986851414},
{"learn":[86.00441746],"iteration":466,"passed_time":0.8732494791,"remaining_time":0.9966637524},
{"learn":[85.97811225],"iteration":467,"passed_time":0.8749734484,"remaining_time":0.9946279371},
{"learn":[85.96731987],"iteration":468,"passed_time":0.876687504,"remaining_time":0.9925822273},
{"learn":[85.89145037],"iteration":469,"passed_time":0.8784448828,"remaining_time":0.9905867827},
{"learn":[85.84634196],"iteration":470,"passed_time":0.8803448988,"remaining_time":0.9887525508},
{"learn":[85.83661129],"iteration":471,"passed_time":0.8820233157,"remaining_time":0.9866701498},
{"learn":[85.8327578],"iteration":472,"passed_time":0.8836760445,"remaining_time":0.984560836},
{"learn":[85.82570295],"iteration":473,"passed_time":0.8853142919,"remaining_time":0.9824373788},
{"learn":[85.82196192],"iteration":474,"passed_time":0.8869573326,"remaining_time":0.9803212624},
{"learn":[85.81661593],"iteration":475,"passed_time":0.888617936,"remaining_time":0.9782264674},
{"learn":[85.79175834],"iteration":476,"passed_time":0.8903409925,"remaining_time":0.9762019687},
{"learn":[85.78637367],"iteration":477,"passed_time":0.8919771416,"remaining_time":0.974083824},
{"learn":[85.77006139],"iteration":478,"passed_time":0.8936329246,"remaining_time":0.9719890475},
{"learn":[85.75590444],"iteration":479,"passed_time":0.8953283104,"remaining_time":0.969939003},
{"learn":[85.73046718],"iteration":480,"passed_time":0.8970248887,"remaining_time":0.9678917199},
{"learn":[85.69035844],"iteration":481,"passed_time":0.8987570965,"remaining_time":0.9658841826},
{"learn":[85.65541009],"iteration":482,"passed_time":0.900479133,"remaining_time":0.9638668981},
{"learn":[85.65158867],"iteration":483,"passed_time":0.9021814357,"remaining_time":0.9618297951},
{"learn":[85.59512148],"iteration":484,"passed_time":0.9039010527,"remaining_time":0.959812458},
{"learn":[85.56663725],"iteration":485,"passed_time":0.905649553,"remaining_time":0.9578268935},
{"learn":[85.54079001],"iteration":486,"passed_time":0.9073670342,"remaining_time":0.9558096274},
{"learn":[85.50721857],"iteration":487,"passed_time":0.9090935576,"remaining_time":0.9538030769},
{"learn":[85.43737459],"iteration":488,"passed_time":0.9108756226,"remaining_time":0.9518557119},
{"learn":[85.42941623],"iteration":489,"passed_time":0.9125498371,"remaining_time":0.9497967692},
{"learn":[85.40332397],"iteration":490,"passed_time":0.9142537886,"remaining_time":0.9477702207},
{"learn":[85.37203622],"iteration":491,"passed_time":0.9160519709,"remaining_time":0.9458422789},
{"learn":[85.31501576],"iteration":492,"passed_time":0.9178066561,"remaining_time":0.9438701311},
{"learn":[85.27474212],"iteration":493,"passed_time":0.9195351939,"remaining_time":0.9418720812},
{"learn":[85.25183977],"iteration":494,"passed_time":0.9212441922,"remaining_time":0.9398551859},
{"learn":[85.22169927],"iteration":495,"passed_time":0.9229630645,"remaining_time":0.9378495656},
{"learn":[85.21626097],"iteration":496,"passed_time":0.9246158782,"remaining_time":0.935778243},
{"learn":[85.19189787],"iteration":497,"passed_time":0.9263132814,"remaining_time":0.9337535487},
{"learn":[85.18519108],"iteration":498,"passed_time":0.9279719158,"remaining_time":0.9316912421},
{"learn":[85.17490877],"iteration":499,"passed_time":0.9296695611,"remaining_time":0.9296695611},
{"learn":[85.12398437],"iteration":500,"passed_time":0.9314327602,"remaining_time":0.9277144657},
{"learn":[85.11893051],"iteration":501,"passed_time":0.9331606622,"remaining_time":0.9257251191},
{"learn":[85.09888649],"iteration":502,"passed_time":0.9348825911,"remaining_time":0.9237309101},
{"learn":[85.06274552],"iteration":503,"passed_time":0.9366291974,"remaining_time":0.9217620673},
{"learn":[85.03175648],"iteration":504,"passed_time":0.9383622326,"remaining_time":0.9197808022},
{"learn":[85.01465888],"iteration":505,"passed_time":0.9400305947,"remaining_time":0.917737379},
{"learn":[85.00899765],"iteration":506,"passed_time":0.9416587366,"remaining_time":0.9156563258},
{"learn":[84.97434799],"iteration":507,"passed_time":0.9433601291,"remaining_time":0.9136479991},
{"learn":[84.9708486],"iteration":508,"passed_time":0.945010238,"remaining_time":0.9115914083},
{"learn":[84.92757941],"iteration":509,"passed_time":0.9467231053,"remaining_time":0.9095967091},
{"learn":[84.88074525],"iteration":510,"passed_time":0.9486120098,"remaining_time":0.907771571},
{"learn":[84.85730883],"iteration":511,"passed_time":0.9503482078,"remaining_time":0.9058006355},
{"learn":[84.80630614],"iteration":512,"passed_time":0.9521642613,"remaining_time":0.9039064235},
{"learn":[84.77188287],"iteration":513,"passed_time":0.9539224793,"remaining_time":0.9019578306},
{"learn":[84.76815219],"iteration":514,"passed_time":0.9555790083,"remaining_time":0.8999142117},
{"learn":[84.76291721],"iteration":515,"passed_time":0.9572511549,"remaining_time":0.8978867422},
{"learn":[84.75952829],"iteration":516,"passed_time":0.9588854766,"remaining_time":0.8958253099},
{"learn":[84.75422662],"iteration":517,"passed_time":0.9605292685,"remaining_time":0.8937743386},
{"learn":[84.72739197],"iteration":518,"passed_time":0.9622437881,"remaining_time":0.8917904857},
{"learn":[84.67903948],"iteration":519,"passed_time":0.9639874995,"remaining_time":0.8898346149},
{"learn":[84.65816665],"iteration":520,"passed_time":0.9656743928,"remaining_time":0.8878273209},
{"learn":[84.62411095],"iteration":521,"passed_time":0.9674338134,"remaining_time":0.8858876682},
{"learn":[84.58191428],"iteration":522,"passed_time":0.970222944,"remaining_time":0.8848878476},
{"learn":[84.5443212],"iteration":523,"passed_time":0.9719722195,"remaining_time":0.8829365963},
{"learn":[84.51182896],"iteration":524,"passed_time":0.9737070162,"remaining_time":0.8809730147},
{"learn":[84.47951485],"iteration":525,"passed_time":0.9754427036,"remaining_time":0.8790111055},
{"learn":[84.46608159],"iteration":526,"passed_time":0.9771724661,"remaining_time":0.8770447372},
{"learn":[84.43138901],"iteration":527,"passed_time":0.9788877591,"remaining_time":0.8750663301},
{"learn":[84.39526118],"iteration":528,"passed_time":0.980708666,"remaining_time":0.8731829521},
{"learn":[84.39009361],"iteration":529,"passed_time":0.9823511067,"remaining_time":0.8711415475},
{"learn":[84.30543533],"iteration":530,"passed_time":0.9841444993,"remaining_time":0.8692349721},
{"learn":[84.27100489],"iteration":531,"passed_time":0.9858725007,"remaining_time":0.8672712976},
{"learn":[84.2352038],"iteration":532,"passed_time":0.9875755833,"remaining_time":0.8652866743},
{"learn":[84.18884462],"iteration":533,"passed_time":0.9893254818,"remaining_time":0.8633439598},
{"learn":[84.16650558],"iteration":534,"passed_time":0.9910313883,"remaining_time":0.86136373},
{"learn":[84.13461005],"iteration":535,"passed_time":0.9927444666,"remaining_time":0.8593907322},
{"learn":[84.04672494],"iteration":536,"passed_time":0.9945135207,"remaining_time":0.8574669648},
{"learn":[83.99824706],"iteration":537,"passed_time":0.9962475245,"remaining_time":0.8555136734},
{"learn":[83.96917701],"iteration":538,"passed_time":0.9979555271,"remaining_time":0.8535389574},
{"learn":[83.93424238],"iteration":539,"passed_time":0.9996846496,"remaining_time":0.8515832201},
{"learn":[83.92360446],"iteration":540,"passed_time":1.001354768,"remaining_time":0.8495782594},
{"learn":[83.91896888],"iteration":541,"passed_time":1.003013182,"remaining_time":0.8475646445},
{"learn":[83.88448831],"iteration":542,"passed_time":1.004731307,"remaining_time":0.8456025914},
{"learn":[83.85876636],"iteration":543,"passed_time":1.006454727,"remaining_time":0.8436458737},
{"learn":[83.83660068],"iteration":544,"passed_time":1.008170264,"remaining_time":0.8416834314},
{"learn":[83.80909399],"iteration":545,"passed_time":1.009903453,"remaining_time":0.8397365711},
{"learn":[83.75720209],"iteration":546,"passed_time":1.011633324,"remaining_time":0.837787744},
{"learn":[83.6830511],"iteration":547,"passed_time":1.013381087,"remaining_time":0.8358544729},
{"learn":[83.65256199],"iteration":548,"passed_time":1.015113177,"remaining_time":0.8339090032},
{"learn":[83.63935709],"iteration":549,"passed_time":1.016815626,"remaining_time":0.8319400575},
{"learn":[83.61943959],"iteration":550,"passed_time":1.01851639,"remaining_time":0.8299707063},
{"learn":[83.60691449],"iteration":551,"passed_time":1.020172768,"remaining_time":0.8279663044},
{"learn":[83.59631104],"iteration":552,"passed_time":1.021890704,"remaining_time":0.8260129198},
{"learn":[83.56110672],"iteration":553,"passed_time":1.023605922,"remaining_time":0.8240581971},
{"learn":[83.54033921],"iteration":554,"passed_time":1.025312061,"remaining_time":0.822097058},
{"learn":[83.5362864],"iteration":555,"passed_time":1.026941937,"remaining_time":0.8200759355},
{"learn":[83.50362099],"iteration":556,"passed_time":1.028693203,"remaining_time":0.8181527626},
{"learn":[83.45871589],"iteration":557,"passed_time":1.03044779,"remaining_time":0.8162328371},
{"learn":[83.4350875],"iteration":558,"passed_time":1.032168624,"remaining_time":0.8142868749},
{"learn":[83.42244462],"iteration":559,"passed_time":1.033890802,"remaining_time":0.8123427732},
{"learn":[83.41496576],"iteration":560,"passed_time":1.03556744,"remaining_time":0.8103638255},
{"learn":[83.39822672],"iteration":561,"passed_time":1.037270066,"remaining_time":0.8084062079},
{"learn":[83.36587162],"iteration":562,"passed_time":1.039018299,"remaining_time":0.8064848961},
{"learn":[83.36257166],"iteration":563,"passed_time":1.040643411,"remaining_time":0.8044690196},
{"learn":[83.32397171],"iteration":564,"passed_time":1.04236798,"remaining_time":0.8025311},
{"learn":[83.30816248],"iteration":565,"passed_time":1.044050222,"remaining_time":0.8005614777},
{"learn":[83.3001096],"iteration":566,"passed_time":1.045706164,"remaining_time":0.798572785},
{"learn":[83.2761444],"iteration":567,"passed_time":1.047420842,"remaining_time":0.7966299362},
{"learn":[83.27264274],"iteration":568,"passed_time":1.049042605,"remaining_time":0.7946175094},
{"learn":[83.26172306],"iteration":569,"passed_time":1.050707208,"remaining_time":0.7926387712},
{"learn":[83.22728182],"iteration":570,"passed_time":1.052451677,"remaining_time":0.7907211374},
{"learn":[83.19491992],"iteration":571,"passed_time":1.054188631,"remaining_time":0.7887984858},
{"learn":[83.19148891],"iteration":572,"passed_time":1.055813863,"remaining_time":0.786793228},
{"learn":[83.14746391],"iteration":573,"passed_time":1.057562364,"remaining_time":0.7848807786},
{"learn":[83.14402843],"iteration":574,"passed_time":1.059207047,"remaining_time":0.7828921651},
{"learn":[83.13730718],"iteration":575,"passed_time":1.060877638,"remaining_time":0.780923817},
{"learn":[83.13308411],"iteration":576,"passed_time":1.062507112,"remaining_time":0.7789263577},
{"learn":[83.10854858],"iteration":577,"passed_time":1.064248586,"remaining_time":0.7770119435},
{"learn":[83.09960518],"iteration":578,"passed_time":1.065923107,"remaining_time":0.7750494439},
{"learn":[83.09268604],"iteration":579,"passed_time":1.067581233,"remaining_time":0.7730760652},
{"learn":[83.06636426],"iteration":580,"passed_time":1.069275314,"remaining_time":0.7711297016},
{"learn":[83.02398526],"iteration":581,"passed_time":1.07100277,"remaining_time":0.769208175},
{"learn":[83.01105904],"iteration":582,"passed_time":1.072678222,"remaining_time":0.7672501176},
{"learn":[83.0069767],"iteration":583,"passed_time":1.074326113,"remaining_time":0.7652733956},
{"learn":[83.00364841],"iteration":584,"passed_time":1.075942304,"remaining_time":0.7632753099},
{"learn":[83.00058417],"iteration":585,"passed_time":1.077588962,"remaining_time":0.7613000516},
{"learn":[82.9719867],"iteration":586,"passed_time":1.079336334,"remaining_time":0.7593967731},
{"learn":[82.93920386],"iteration":587,"passed_time":1.08105581,"remaining_time":0.7574744791},
{"learn":[82.91813511],"iteration":588,"passed_time":1.082761095,"remaining_time":0.755542971},
{"learn":[82.91465998],"iteration":589,"passed_time":1.084386649,"remaining_time":0.7535568242},
{"learn":[82.9112547],"iteration":590,"passed_time":1.086012508,"remaining_time":0.7515721078},
{"learn":[82.90295185],"iteration":591,"passed_time":1.08784122,"remaining_time":0.7497284081},
{"learn":[82.88754005],"iteration":592,"passed_time":1.089557696,"remaining_time":0.747807727},
{"learn":[82.84765937],"iteration":593,"passed_time":1.09130512,"remaining_time":0.7459088868},
{"learn":[82.80271047],"iteration":594,"passed_time":1.093091124,"remaining_time":0.7440368154},
{"learn":[82.77172575],"iteration":595,"passed_time":1.094798499,"remaining_time":0.7421117343},
{"learn":[82.73934866],"iteration":596,"passed_time":1.096560057,"remaining_time":0.7402239583},
{"learn":[82.69673381],"iteration":597,"passed_time":1.098300192,"remaining_time":0.7383222026},
{"learn":[82.66975959],"iteration":598,"passed_time":1.100026885,"remaining_time":0.736411988},
{"learn":[82.62851111],"iteration":599,"passed_time":1.101776734,"remaining_time":0.7345178228},
{"learn":[82.58767939],"iteration":600,"passed_time":1.103519429,"remaining_time":0.732619388},
{"learn":[82.57421648],"iteration":601,"passed_time":1.105232665,"remaining_time":0.7307019945},
{"learn":[82.57100434],"iteration":602,"passed_time":1.106886182,"remaining_time":0.7287459609},
{"learn":[82.54007044],"iteration":603,"passed_time":1.108630687,"remaining_time":0.7268505831},
{"learn":[82.5094686],"iteration":604,"passed_time":1.110343605,"remaining_time":0.7249350808},
{"learn":[82.50630901],"iteration":605,"passed_time":1.111996669,"remaining_time":0.7229813324},
{"learn":[82.47316073],"iteration":606,"passed_time":1.113741734,"remaining_time":0.7210881407},
{"learn":[82.43628436],"iteration":607,"passed_time":1.115514027,"remaining_time":0.7192129911},
{"learn":[82.42067539],"iteration":608,"passed_time":1.117245278,"remaining_time":0.7173118287},
{"learn":[82.3763233],"iteration":609,"passed_time":1.119000884,"remaining_time":0.7154267946},
{"learn":[82.3684768],"iteration":610,"passed_time":1.120666805,"remaining_time":0.7134850851},
{"learn":[82.32539029],"iteration":611,"passed_time":1.122425043,"remaining_time":0.7116028051},
{"learn":[82.29800019],"iteration":612,"passed_time":1.124163695,"remaining_time":0.7097085647},
{"learn":[82.28353105],"iteration":613,"passed_time":1.125843285,"remaining_time":0.7077777006},
{"learn":[82.28048811],"iteration":614,"passed_time":1.127474074,"remaining_time":0.7058171034},
{"learn":[82.27723543],"iteration":615,"passed_time":1.129121133,"remaining_time":0.7038677191},
{"learn":[82.27293434],"iteration":616,"passed_time":1.130768697,"remaining_time":0.7019196288},
{"learn":[82.25489951],"iteration":617,"passed_time":1.132499305,"remaining_time":0.7000238424},
{"learn":[82.22597604],"iteration":618,"passed_time":1.134179088,"remaining_time":0.698097306},
{"learn":[82.1899227],"iteration":619,"passed_time":1.135925193,"remaining_time":0.6962122153},
{"learn":[82.17902155],"iteration":620,"passed_time":1.13758105,"remaining_time":0.6942724928},
{"learn":[82.1529213],"iteration":621,"passed_time":1.139310841,"remaining_time":0.6923786142},
{"learn":[82.12393713],"iteration":622,"passed_time":1.141039201,"remaining_time":0.6904843961},
{"learn":[82.09060189],"iteration":623,"passed_time":1.142769435,"remaining_time":0.6885918393},
{"learn":[82.0545917],"iteration":624,"passed_time":1.144555064,"remaining_time":0.6867330387},
{"learn":[82.0184237],"iteration":625,"passed_time":1.146297371,"remaining_time":0.6848485891},
{"learn":[81.97802847],"iteration":626,"passed_time":1.148051189,"remaining_time":0.6829714409},
{"learn":[81.9499904],"iteration":627,"passed_time":1.149799881,"remaining_time":0.6810916492},
{"learn":[81.93446173],"iteration":628,"passed_time":1.151509948,"remaining_time":0.6791894926},
{"learn":[81.93136345],"iteration":629,"passed_time":1.153147442,"remaining_time":0.6772453231},
{"learn":[81.90194967],"iteration":630,"passed_time":1.154880938,"remaining_time":0.6753582663},
{"learn":[81.8836477],"iteration":631,"passed_time":1.156583402,"remaining_time":0.6734536266},
{"learn":[81.87329626],"iteration":632,"passed_time":1.158257337,"remaining_time":0.671533085},
{"learn":[81.87009983],"iteration":633,"passed_time":1.15996404,"remaining_time":0.6696322378},
{"learn":[81.86621516],"iteration":634,"passed_time":1.16162955,"remaining_time":0.6677083239},
{"learn":[81.84406638],"iteration":635,"passed_time":1.163329537,"remaining_time":0.665804955},
{"learn":[81.82292072],"iteration":636,"passed_time":1.165202328,"remaining_time":0.6640006988},
{"learn":[81.80425075],"iteration":637,"passed_time":1.166913833,"remaining_time":0.6621047138},
{"learn":[81.77631279],"iteration":638,"passed_time":1.168648171,"remaining_time":0.6602222064},
{"learn":[81.76842209],"iteration":639,"passed_time":1.170340785,"remaining_time":0.6583166917},
{"learn":[81.76467626],"iteration":640,"passed_time":1.171977244,"remaining_time":0.6563803912},
{"learn":[81.75388445],"iteration":641,"passed_time":1.173662569,"remaining_time":0.6544722736},
{"learn":[81.74054454],"iteration":642,"passed_time":1.175347396,"remaining_time":0.6525645727},
{"learn":[81.73687722],"iteration":643,"passed_time":1.176988886,"remaining_time":0.6506336078},
{"learn":[81.73396997],"iteration":644,"passed_time":1.178716806,"remaining_time":0.6487511102},
{"learn":[81.69357502],"iteration":645,"passed_time":1.180488904,"remaining_time":0.6468933003},
{"learn":[81.65719605],"iteration":646,"passed_time":1.182242969,"remaining_time":0.6450259165},
{"learn":[81.65368411],"iteration":647,"passed_time":1.183887715,"remaining_time":0.6430994996},
{"learn":[81.65085376],"iteration":648,"passed_time":1.18552227,"remaining_time":0.6411684388},
{"learn":[81.64781752],"iteration":649,"passed_time":1.187159845,"remaining_time":0.6392399166},
{"learn":[81.61652837],"iteration":650,"passed_time":1.188869159,"remaining_time":0.6373507473},
{"learn":[81.60543257],"iteration":651,"passed_time":1.190538465,"remaining_time":0.6354407757},
{"learn":[81.5935818],"iteration":652,"passed_time":1.192201312,"remaining_time":0.6335281091},
{"learn":[81.59080919],"iteration":653,"passed_time":1.193841361,"remaining_time":0.631604145},
{"learn":[81.56756551],"iteration":654,"passed_time":1.195575563,"remaining_time":0.6297306399},
{"learn":[81.55409843],"iteration":655,"passed_time":1.197284964,"remaining_time":0.6278445545},
{"learn":[81.55051436],"iteration":656,"passed_time":1.198917675,"remaining_time":0.6259189688},
{"learn":[81.53369382],"iteration":657,"passed_time":1.200658786,"remaining_time":0.624050615},
{"learn":[81.4964051],"iteration":658,"passed_time":1.20240403,"remaining_time":0.6221847865},
{"learn":[81.46299661],"iteration":659,"passed_time":1.204145919,"remaining_time":0.6203175949},
{"learn":[81.41197655],"iteration":660,"passed_time":1.205895505,"remaining_time":0.6184547296},
{"learn":[81.38557738],"iteration":661,"passed_time":1.207636313,"remaining_time":0.616587725},
{"learn":[81.38282802],"iteration":662,"passed_time":1.209282101,"remaining_time":0.6146728024},
{"learn":[81.38002508],"iteration":663,"passed_time":1.210909604,"remaining_time":0.6127494382},
{"learn":[81.37677099],"iteration":664,"passed_time":1.212560653,"remaining_time":0.6108388253},
{"learn":[81.35666164],"iteration":665,"passed_time":1.214264378,"remaining_time":0.6089554088},
{"learn":[81.31176778],"iteration":666,"passed_time":1.216002014,"remaining_time":0.6070894612},
{"learn":[81.26111814],"iteration":667,"passed_time":1.217732796,"remaining_time":0.6052204916},
{"learn":[81.25838995],"iteration":668,"passed_time":1.219388251,"remaining_time":0.6033146653},
{"learn":[81.22260289],"iteration":669,"passed_time":1.221136012,"remaining_time":0.6014550506},
{"learn":[81.20743497],"iteration":670,"passed_time":1.222876309,"remaining_time":0.5995921098},
{"learn":[81.20443722],"iteration":671,"passed_time":1.224518388,"remaining_time":0.5976815942},
{"learn":[81.19188576],"iteration":672,"passed_time":1.226242813,"remaining_time":0.5958118868},
{"learn":[81.16543429],"iteration":673,"passed_time":1.227965976,"remaining_time":0.5939420001},
{"learn":[81.16277401],"iteration":674,"passed_time":1.229602461,"remaining_time":0.5920308144},
{"learn":[81.16021047],"iteration":675,"passed_time":1.231226957,"remaining_time":0.5901146956},
{"learn":[81.13975787],"iteration":676,"passed_time":1.232962314,"remaining_time":0.5882523301},
{"learn":[81.13064901],"iteration":677,"passed_time":1.234631283,"remaining_time":0.5863588098},
{"learn":[81.10658896],"iteration":678,"passed_time":1.236375599,"remaining_time":0.5845015718},
{"learn":[81.10353797],"iteration":679,"passed_time":1.237992755,"remaining_time":0.5825848258},
{"learn":[81.06209375],"iteration":680,"passed_time":1.239728907,"remaining_time":0.5807247008},
{"learn":[81.05254606],"iteration":681,"passed_time":1.241402963,"remaining_time":0.5788359859},
{"learn":[81.03141931],"iteration":682,"passed_time":1.243105446,"remaining_time":0.5769610928},
{"learn":[81.02286935],"iteration":683,"passed_time":1.244794112,"remaining_time":0.5750803207},
{"learn":[81.00073964],"iteration":684,"passed_time":1.246524636,"remaining_time":0.5732193582},
{"learn":[80.96404468],"iteration":685,"passed_time":1.248258244,"remaining_time":0.5713601876},
{"learn":[80.92084098],"iteration":686,"passed_time":1.249993399,"remaining_time":0.5695020872},
{"learn":[80.90132926],"iteration":687,"passed_time":1.251787058,"remaining_time":0.5676708751},
{"learn":[80.89873726],"iteration":688,"passed_time":1.253418253,"remaining_time":0.5657664393},
{"learn":[80.87618005],"iteration":689,"passed_time":1.255133765,"remaining_time":0.5639006769},
{"learn":[80.86430172],"iteration":690,"passed_time":1.256837553,"remaining_time":0.562030107},
{"learn":[80.84305485],"iteration":691,"passed_time":1.258574237,"remaining_time":0.5601746606},
{"learn":[80.80391535],"iteration":692,"passed_time":1.260313049,"remaining_time":0.5583204994},
{"learn":[80.80137543],"iteration":693,"passed_time":1.261963306,"remaining_time":0.5564276247},
{"learn":[80.75415389],"iteration":694,"passed_time":1.26371187,"remaining_time":0.5545785903},
{"learn":[80.75104538],"iteration":695,"passed_time":1.265365184,"remaining_time":0.5526882413},
{"learn":[80.74849446],"iteration":696,"passed_time":1.267014344,"remaining_time":0.5507967664},
{"learn":[80.71256539],"iteration":697,"passed_time":1.268763876,"remaining_time":0.5489494135},
{"learn":[80.70789769],"iteration":698,"passed_time":1.270455234,"remaining_time":0.5470772898},
{"learn":[80.64725209],"iteration":699,"passed_time":1.272229875,"remaining_time":0.5452413749},
{"learn":[80.60295574],"iteration":700,"passed_time":1.273980191,"remaining_time":0.5433952599},
{"learn":[80.6004814],"iteration":701,"passed_time":1.275626356,"remaining_time":0.5415052054},
{"learn":[80.57704738],"iteration":702,"passed_time":1.277343915,"remaining_time":0.5396460068},
{"learn":[80.53698301],"iteration":703,"passed_time":1.279077477,"remaining_time":0.537793939},
{"learn":[80.51435668],"iteration":704,"passed_time":1.280800621,"remaining_time":0.5359378485},
{"learn":[80.51142932],"iteration":705,"passed_time":1.282498234,"remaining_time":0.5340715025},
{"learn":[80.50297868],"iteration":706,"passed_time":1.2842173,"remaining_time":0.5322145246},
{"learn":[80.44262068],"iteration":707,"passed_time":1.285987205,"remaining_time":0.5303789038},
{"learn":[80.43325515],"iteration":708,"passed_time":1.287682652,"remaining_time":0.5285129079},
{"learn":[80.42562142],"iteration":709,"passed_time":1.289355981,"remaining_time":0.5266383583},
{"learn":[80.38973082],"iteration":710,"passed_time":1.291105721,"remaining_time":0.5247954339},
{"learn":[80.38119987],"iteration":711,"passed_time":1.29279154,"remaining_time":0.5229269152},
{"learn":[80.37846052],"iteration":712,"passed_time":1.294443429,"remaining_time":0.5210452511},
{"learn":[80.34033745],"iteration":713,"passed_time":1.296233392,"remaining_time":0.519219538},
{"learn":[80.32425067],"iteration":714,"passed_time":1.29797143,"remaining_time":0.5173732274},
{"learn":[80.32186703],"iteration":715,"passed_time":1.299631727,"remaining_time":0.5154963834},
{"learn":[80.3115422],"iteration":716,"passed_time":1.30129753,"remaining_time":0.5136223167},
{"learn":[80.3086523],"iteration":717,"passed_time":1.302933344,"remaining_time":0.5117370517},
{"learn":[80.2765144],"iteration":718,"passed_time":1.304646162,"remaining_time":0.5098825753},
{"learn":[80.26147174],"iteration":719,"passed_time":1.306354435,"remaining_time":0.5080267248},
{"learn":[80.24828278],"iteration":720,"passed_time":1.308365464,"remaining_time":0.5062884391},
{"learn":[80.22664039],"iteration":721,"passed_time":1.310097733,"remaining_time":0.5044420633},
{"learn":[80.22438582],"iteration":722,"passed_time":1.311747677,"remaining_time":0.5025644628},
{"learn":[80.19012314],"iteration":723,"passed_time":1.313500219,"remaining_time":0.5007266028},
{"learn":[80.18257237],"iteration":724,"passed_time":1.315183539,"remaining_time":0.4988627218},
{"learn":[80.15462074],"iteration":725,"passed_time":1.316922961,"remaining_time":0.4970205115},
{"learn":[80.11719096],"iteration":726,"passed_time":1.318654351,"remaining_time":0.4951755677},
{"learn":[80.10939228],"iteration":727,"passed_time":1.320348339,"remaining_time":0.4933169619},
{"learn":[80.09112059],"iteration":728,"passed_time":1.322048388,"remaining_time":0.4914610605},
{"learn":[80.06697331],"iteration":729,"passed_time":1.323905181,"remaining_time":0.4896635602},
{"learn":[80.06055489],"iteration":730,"passed_time":1.325620332,"remaining_time":0.4878137748},
{"learn":[80.04334607],"iteration":731,"passed_time":1.327327916,"remaining_time":0.4859615868},
{"learn":[80.022346],"iteration":732,"passed_time":1.329021567,"remaining_time":0.4841047181},
{"learn":[79.98770917],"iteration":733,"passed_time":1.330750909,"remaining_time":0.4822612286},
{"learn":[79.98512209],"iteration":734,"passed_time":1.332397499,"remaining_time":0.4803882141},
{"learn":[79.97734508],"iteration":735,"passed_time":1.334064275,"remaining_time":0.478523055},
{"learn":[79.97497281],"iteration":736,"passed_time":1.335710966,"remaining_time":0.4766512673},
{"learn":[79.95729892],"iteration":737,"passed_time":1.337410012,"remaining_time":0.4747986762},
{"learn":[79.93578514],"iteration":738,"passed_time":1.339135572,"remaining_time":0.4729558649},
{"learn":[79.92868861],"iteration":739,"passed_time":1.340809233,"remaining_time":0.4710951359},
{"learn":[79.91094945],"iteration":740,"passed_time":1.342555141,"remaining_time":0.4692601639},
{"learn":[79.86964162],"iteration":741,"passed_time":1.344294262,"remaining_time":0.4674230723},
{"learn":[79.85524953],"iteration":742,"passed_time":1.346166002,"remaining_time":0.4656321165},
{"learn":[79.83139587],"iteration":743,"passed_time":1.347913387,"remaining_time":0.4637981546},
{"learn":[79.82931343],"iteration":744,"passed_time":1.349694404,"remaining_time":0.461975937},
{"learn":[79.81989057],"iteration":745,"passed_time":1.351369593,"remaining_time":0.460117797},
{"learn":[79.76178659],"iteration":746,"passed_time":1.353133151,"remaining_time":0.4582900766},
{"learn":[79.7505951],"iteration":747,"passed_time":1.354831211,"remaining_time":0.4564404616},
{"learn":[79.73618907],"iteration":748,"passed_time":1.356554222,"remaining_time":0.4545996123},
{"learn":[79.69560823],"iteration":749,"passed_time":1.358370103,"remaining_time":0.4527900345},
{"learn":[79.66954943],"iteration":750,"passed_time":1.360100419,"remaining_time":0.4509520698},
{"learn":[79.66698339],"iteration":751,"passed_time":1.361763405,"remaining_time":0.4490921867},
{"learn":[79.66430098],"iteration":752,"passed_time":1.363404895,"remaining_time":0.4472257757},
{"learn":[79.62390016],"iteration":753,"passed_time":1.365155456,"remaining_time":0.4453955465},
{"learn":[79.61723731],"iteration":754,"passed_time":1.366838367,"remaining_time":0.4435435762},
{"learn":[79.61500959],"iteration":755,"passed_time":1.368470175,"remaining_time":0.4416755593},
{"learn":[79.59519222],"iteration":756,"passed_time":1.370197834,"remaining_time":0.4398389349},
{"learn":[79.54308003],"iteration":757,"passed_time":1.371962007,"remaining_time":0.4380142556},
{"learn":[79.5409043],"iteration":758,"passed_time":1.373607616,"remaining_time":0.436152089},
{"learn":[79.49271715],"iteration":759,"passed_time":1.375360692,"remaining_time":0.434324429},
{"learn":[79.48413983],"iteration":760,"passed_time":1.377040173,"remaining_time":0.4324738519},
{"learn":[79.47701543],"iteration":761,"passed_time":1.378900649,"remaining_time":0.4306802551},
{"learn":[79.47496512],"iteration":762,"passed_time":1.380630362,"remaining_time":0.4288458662},
{"learn":[79.43296424],"iteration":763,"passed_time":1.382395166,"remaining_time":0.4270225906},
{"learn":[79.40637318],"iteration":764,"passed_time":1.384124437,"remaining_time":0.4251885526},
{"learn":[79.3667859],"iteration":765,"passed_time":1.38586367,"remaining_time":0.4233578314},
{"learn":[79.34596901],"iteration":766,"passed_time":1.387600016,"remaining_time":0.4215264717},
{"learn":[79.32554803],"iteration":767,"passed_time":1.389301304,"remaining_time":0.4196847689},
{"learn":[79.3151977],"iteration":768,"passed_time":1.390999376,"remaining_time":0.4178424654},
{"learn":[79.31259446],"iteration":769,"passed_time":1.392619726,"remaining_time":0.4159773208},
{"learn":[79.29360324],"iteration":770,"passed_time":1.394320176,"remaining_time":0.4141366022},
{"learn":[79.23871583],"iteration":771,"passed_time":1.396076203,"remaining_time":0.4123126611},
{"learn":[79.22334058],"iteration":772,"passed_time":1.397788463,"remaining_time":0.4104760428},
{"learn":[79.22102785],"iteration":773,"passed_time":1.399409338,"remaining_time":0.4086130626},
{"learn":[79.19211507],"iteration":774,"passed_time":1.40114474,"remaining_time":0.4067839567},
{"learn":[79.16575611],"iteration":775,"passed_time":1.402870794,"remaining_time":0.404952394},
{"learn":[79.15754959],"iteration":776,"passed_time":1.404568311,"remaining_time":0.4031129129},
{"learn":[79.13565022],"iteration":777,"passed_time":1.406315203,"remaining_time":0.4012878857},
{"learn":[79.12134059],"iteration":778,"passed_time":1.408108906,"remaining_time":0.3994763391},
{"learn":[79.09468074],"iteration":779,"passed_time":1.40983213,"remaining_time":0.3976449599},
{"learn":[79.07148029],"iteration":780,"passed_time":1.411554898,"remaining_time":0.3958137293},
{"learn":[79.06928335],"iteration":781,"passed_time":1.413195887,"remaining_time":0.3939599786},
{"learn":[79.06729764],"iteration":782,"passed_time":1.414837024,"remaining_time":0.3921068125},
{"learn":[79.04650111],"iteration":783,"passed_time":1.416565095,"remaining_time":0.3902781385},
{"learn":[79.04426804],"iteration":784,"passed_time":1.418184012,"remaining_time":0.388419825},
{"learn":[79.01265519],"iteration":785,"passed_time":1.420027051,"remaining_time":0.3866231411},
{"learn":[78.98529308],"iteration":786,"passed_time":1.421881398,"remaining_time":0.3848293999},
{"learn":[78.98313525],"iteration":787,"passed_time":1.423529932,"remaining_time":0.382980134},
{"learn":[78.95944224],"iteration":788,"passed_time":1.425267643,"remaining_time":0.3811552253},
{"learn":[78.92343826],"iteration":789,"passed_time":1.427029863,"remaining_time":0.3793370523},
{"learn":[78.91626213],"iteration":790,"passed_time":1.428703434,"remaining_time":0.3774955976},
{"learn":[78.91412486],"iteration":791,"passed_time":1.430360259,"remaining_time":0.375650169},
{"learn":[78.8932417],"iteration":792,"passed_time":1.432048922,"remaining_time":0.3738135269},
{"learn":[78.8911377],"iteration":793,"passed_time":1.433807388,"remaining_time":0.3719953676},
{"learn":[78.88907129],"iteration":794,"passed_time":1.435426742,"remaining_time":0.3701414869},
{"learn":[78.88669629],"iteration":795,"passed_time":1.437127685,"remaining_time":0.3683091052},
{"learn":[78.86831399],"iteration":796,"passed_time":1.438837772,"remaining_time":0.3664793823},
{"learn":[78.84385638],"iteration":797,"passed_time":1.440548927,"remaining_time":0.3646502296},
{"learn":[78.83617247],"iteration":798,"passed_time":1.442213115,"remaining_time":0.3628095571},
{"learn":[78.83411676],"iteration":799,"passed_time":1.443831537,"remaining_time":0.3609578843},
{"learn":[78.80450812],"iteration":800,"passed_time":1.445580767,"remaining_time":0.3591392916},
{"learn":[78.79681485],"iteration":801,"passed_time":1.447237247,"remaining_time":0.3572979736},
{"learn":[78.75440239],"iteration":802,"passed_time":1.448995078,"remaining_time":0.3554819806},
{"learn":[78.74786454],"iteration":803,"passed_time":1.450685511,"remaining_time":0.3536497016},
{"learn":[78.72418747],"iteration":804,"passed_time":1.452422064,"remaining_time":0.3518289472},
{"learn":[78.70934267],"iteration":805,"passed_time":1.454118993,"remaining_time":0.3499988643},
{"learn":[78.68333694],"iteration":806,"passed_time":1.455871933,"remaining_time":0.3481825068},
{"learn":[78.63267052],"iteration":807,"passed_time":1.457632372,"remaining_time":0.3463680885},
{"learn":[78.60727436],"iteration":808,"passed_time":1.459350829,"remaining_time":0.3445438918},
{"learn":[78.59840958],"iteration":809,"passed_time":1.461010814,"remaining_time":0.3427062403},
{"learn":[78.57209594],"iteration":810,"passed_time":1.462757858,"remaining_time":0.3408893159},
{"learn":[78.53035663],"iteration":811,"passed_time":1.46450571,"remaining_time":0.3390727506},
{"learn":[78.51729515],"iteration":812,"passed_time":1.466224356,"remaining_time":0.3372496365},
{"learn":[78.49103826],"iteration":813,"passed_time":1.467951233,"remaining_time":0.3354286602},
{"learn":[78.48905022],"iteration":814,"passed_time":1.469600147,"remaining_time":0.3335902175},
{"learn":[78.46088789],"iteration":815,"passed_time":1.471340961,"remaining_time":0.3317729617},
{"learn":[78.45847974],"iteration":816,"passed_time":1.472995798,"remaining_time":0.3299366353},
{"learn":[78.44470201],"iteration":817,"passed_time":1.47474241,"remaining_time":0.3281211718},
{"learn":[78.41676674],"iteration":818,"passed_time":1.476500679,"remaining_time":0.326308453},
{"learn":[78.39278938],"iteration":819,"passed_time":1.478229646,"remaining_time":0.3244894344},
{"learn":[78.38528762],"iteration":820,"passed_time":1.479895838,"remaining_time":0.3226569488},
{"learn":[78.34632288],"iteration":821,"passed_time":1.481641113,"remaining_time":0.3208419929},
{"learn":[78.33987451],"iteration":822,"passed_time":1.483464411,"remaining_time":0.3190439862},
{"learn":[78.33039715],"iteration":823,"passed_time":1.485164845,"remaining_time":0.3172196756},
{"learn":[78.30068594],"iteration":824,"passed_time":1.486918945,"remaining_time":0.3154070488},
{"learn":[78.267006],"iteration":825,"passed_time":1.488671573,"remaining_time":0.3135942538},
{"learn":[78.24991106],"iteration":826,"passed_time":1.490388939,"remaining_time":0.3117742279},
{"learn":[78.22463001],"iteration":827,"passed_time":1.492105387,"remaining_time":0.309954259},
{"learn":[78.20237502],"iteration":828,"passed_time":1.493851436,"remaining_time":0.3081406459},
{"learn":[78.17796982],"iteration":829,"passed_time":1.495578938,"remaining_time":0.306323397},
{"learn":[78.16401719],"iteration":830,"passed_time":1.497303742,"remaining_time":0.3045058151},
{"learn":[78.13161182],"iteration":831,"passed_time":1.499121204,"remaining_time":0.3027071662},
{"learn":[78.10716583],"iteration":832,"passed_time":1.500886359,"remaining_time":0.3008979856},
{"learn":[78.1009177],"iteration":833,"passed_time":1.502557105,"remaining_time":0.2990701192},
{"learn":[78.07752137],"iteration":834,"passed_time":1.504309855,"remaining_time":0.2972588335},
{"learn":[78.04874934],"iteration":835,"passed_time":1.506039091,"remaining_time":0.2954430752},
{"learn":[78.02799808],"iteration":836,"passed_time":1.507764943,"remaining_time":0.2936268647},
{"learn":[78.00273893],"iteration":837,"passed_time":1.509532417,"remaining_time":0.291818916},
{"learn":[77.96519282],"iteration":838,"passed_time":1.511284024,"remaining_time":0.2900080189},
{"learn":[77.94300661],"iteration":839,"passed_time":1.513015619,"remaining_time":0.2881934512},
{"learn":[77.90558576],"iteration":840,"passed_time":1.514782199,"remaining_time":0.2863856952},
{"learn":[77.88261027],"iteration":841,"passed_time":1.516535019,"remaining_time":0.2845754548},
{"learn":[77.8517906],"iteration":842,"passed_time":1.518291543,"remaining_time":0.2827660406},
{"learn":[77.82884058],"iteration":843,"passed_time":1.520012655,"remaining_time":0.2809502063},
{"learn":[77.79780593],"iteration":844,"passed_time":1.521776638,"remaining_time":0.2791424602},
{"learn":[77.75935966],"iteration":845,"passed_time":1.523592005,"remaining_time":0.2773441711},
{"learn":[77.7461329],"iteration":846,"passed_time":1.525309015,"remaining_time":0.2755280747},
{"learn":[77.74403483],"iteration":847,"passed_time":1.527033804,"remaining_time":0.2737136064},
{"learn":[77.70772347],"iteration":848,"passed_time":1.528823156,"remaining_time":0.2719108322},
{"learn":[77.66865761],"iteration":849,"passed_time":1.530586505,"remaining_time":0.2701035008},
{"learn":[77.64044687],"iteration":850,"passed_time":1.532320528,"remaining_time":0.2682911383},
{"learn":[77.63838009],"iteration":851,"passed_time":1.533983441,"remaining_time":0.2664666071},
{"learn":[77.60970509],"iteration":852,"passed_time":1.535757125,"remaining_time":0.2646615443},
{"learn":[77.60790407],"iteration":853,"passed_time":1.537390031,"remaining_time":0.2628324877},
{"learn":[77.5948132],"iteration":854,"passed_time":1.53909692,"remaining_time":0.2610164367},
{"learn":[77.58556727],"iteration":855,"passed_time":1.54076267,"remaining_time":0.2591937202},
{"learn":[77.55626001],"iteration":856,"passed_time":1.54250871,"remaining_time":0.2573847672},
{"learn":[77.55412108],"iteration":857,"passed_time":1.544168481,"remaining_time":0.2555616833},
{"learn":[77.5312722],"iteration":858,"passed_time":1.545889543,"remaining_time":0.2537490403},
{"learn":[77.51616921],"iteration":859,"passed_time":1.547597497,"remaining_time":0.2519344762},
{"learn":[77.50216589],"iteration":860,"passed_time":1.549302189,"remaining_time":0.2501196334},
{"learn":[77.46748346],"iteration":861,"passed_time":1.551039532,"remaining_time":0.2483102731},
{"learn":[77.45178425],"iteration":862,"passed_time":1.552765349,"remaining_time":0.2464992501},
{"learn":[77.44646702],"iteration":863,"passed_time":1.554438309,"remaining_time":0.2446801042},
{"learn":[77.43649418],"iteration":864,"passed_time":1.556149775,"remaining_time":0.2428673059},
{"learn":[77.42960326],"iteration":865,"passed_time":1.557867033,"remaining_time":0.2410556379},
{"learn":[77.42749388],"iteration":866,"passed_time":1.559527799,"remaining_time":0.2392355217},
{"learn":[77.42536855],"iteration":867,"passed_time":1.561173315,"remaining_time":0.2374134535},
{"learn":[77.37625829],"iteration":868,"passed_time":1.562927278,"remaining_time":0.2356081397},
{"learn":[77.36216537],"iteration":869,"passed_time":1.564642746,"remaining_time":0.2337971919},
{"learn":[77.34603361],"iteration":870,"passed_time":1.566496744,"remaining_time":0.2320069804},
{"learn":[77.34035024],"iteration":871,"passed_time":1.568173111,"remaining_time":0.2301905484},
{"learn":[77.32174904],"iteration":872,"passed_time":1.569883622,"remaining_time":0.2283794044},
{"learn":[77.31970956],"iteration":873,"passed_time":1.571528251,"remaining_time":0.2265589927},
{"learn":[77.30442185],"iteration":874,"passed_time":1.573242117,"remaining_time":0.2247488738},
{"learn":[77.302648],"iteration":875,"passed_time":1.574886031,"remaining_time":0.2229290728},
{"learn":[77.30080332],"iteration":876,"passed_time":1.576514343,"remaining_time":0.2211074849},
{"learn":[77.28285625],"iteration":877,"passed_time":1.578244878,"remaining_time":0.2193005411},
{"learn":[77.26593482],"iteration":878,"passed_time":1.5799587,"remaining_time":0.2174914706},
{"learn":[77.21197222],"iteration":879,"passed_time":1.58172675,"remaining_time":0.2156900114},
{"learn":[77.21018685],"iteration":880,"passed_time":1.583361059,"remaining_time":0.213870563},
{"learn":[77.20260532],"iteration":881,"passed_time":1.585063188,"remaining_time":0.2120606079},
{"learn":[77.17797231],"iteration":882,"passed_time":1.586754086,"remaining_time":0.2102494089},
{"learn":[77.17282863],"iteration":883,"passed_time":1.588501888,"remaining_time":0.2084459492},
{"learn":[77.15962316],"iteration":884,"passed_time":1.590237697,"remaining_time":0.2066410567},
{"learn":[77.13110954],"iteration":885,"passed_time":1.591984406,"remaining_time":0.2048377226},
{"learn":[77.10924081],"iteration":886,"passed_time":1.593702065,"remaining_time":0.2030308155},
{"learn":[77.10745667],"iteration":887,"passed_time":1.595364033,"remaining_time":0.2012170852},
{"learn":[77.09077269],"iteration":888,"passed_time":1.597090671,"remaining_time":0.1994117711},
{"learn":[77.08915879],"iteration":889,"passed_time":1.598728304,"remaining_time":0.1975956331},
{"learn":[77.07875434],"iteration":890,"passed_time":1.600439907,"remaining_time":0.1957889448},
{"learn":[77.0491016],"iteration":891,"passed_time":1.602167481,"remaining_time":0.1939844036},
{"learn":[77.04068792],"iteration":892,"passed_time":1.603864908,"remaining_time":0.1921764224},
{"learn":[77.03908992],"iteration":893,"passed_time":1.605520558,"remaining_time":0.190363735},
{"learn":[77.03735577],"iteration":894,"passed_time":1.607174893,"remaining_time":0.1885512444},
{"learn":[77.00813334],"iteration":895,"passed_time":1.608926466,"remaining_time":0.1867503933},
{"learn":[77.00047618],"iteration":896,"passed_time":1.610625082,"remaining_time":0.1849435713},
{"learn":[76.99831765],"iteration":897,"passed_time":1.612381727,"remaining_time":0.1831435815},
{"learn":[76.95650644],"iteration":898,"passed_time":1.614158214,"remaining_time":0.1813459172},
{"learn":[76.92639663],"iteration":899,"passed_time":1.615929187,"remaining_time":0.1795476874},
{"learn":[76.90778479],"iteration":900,"passed_time":1.617669665,"remaining_time":0.1777461674},
{"learn":[76.90608914],"iteration":901,"passed_time":1.619321894,"remaining_time":0.1759351947},
{"learn":[76.88544573],"iteration":902,"passed_time":1.62106421,"remaining_time":0.1741342506},
{"learn":[76.85687546],"iteration":903,"passed_time":1.622815334,"remaining_time":0.1723343717},
{"learn":[76.82087572],"iteration":904,"passed_time":1.624594154,"remaining_time":0.1705375079},
{"learn":[76.78398166],"iteration":905,"passed_time":1.62635231,"remaining_time":0.1687385399},
{"learn":[76.78208236],"iteration":906,"passed_time":1.627996361,"remaining_time":0.1669279621},
{"learn":[76.76409689],"iteration":907,"passed_time":1.629805835,"remaining_time":0.1651345119},
{"learn":[76.73654759],"iteration":908,"passed_time":1.631554371,"remaining_time":0.1633349261},
{"learn":[76.71917241],"iteration":909,"passed_time":1.633292017,"remaining_time":0.1615343753},
{"learn":[76.70905017],"iteration":910,"passed_time":1.634980658,"remaining_time":0.1597291752},
{"learn":[76.70300977],"iteration":911,"passed_time":1.636661405,"remaining_time":0.1579234689},
{"learn":[76.69555137],"iteration":912,"passed_time":1.638306298,"remaining_time":0.1561146198},
{"learn":[76.67573429],"iteration":913,"passed_time":1.640027894,"remaining_time":0.1543133467},
{"learn":[76.66891418],"iteration":914,"passed_time":1.6416726,"remaining_time":0.1525051049},
{"learn":[76.66730769],"iteration":915,"passed_time":1.643315025,"remaining_time":0.1506970111},
{"learn":[76.65410159],"iteration":916,"passed_time":1.645008024,"remaining_time":0.148893856},
{"learn":[76.64644134],"iteration":917,"passed_time":1.646677423,"remaining_time":0.147088833},
{"learn":[76.64464117],"iteration":918,"passed_time":1.648313289,"remaining_time":0.1452811495},
{"learn":[76.64288276],"iteration":919,"passed_time":1.649947508,"remaining_time":0.1434736963},
{"learn":[76.62270207],"iteration":920,"passed_time":1.651620785,"remaining_time":0.1416699696},
{"learn":[76.62109559],"iteration":921,"passed_time":1.653256861,"remaining_time":0.1398633787},
{"learn":[76.619341],"iteration":922,"passed_time":1.65488559,"remaining_time":0.1380565444},
{"learn":[76.60304264],"iteration":923,"passed_time":1.656637454,"remaining_time":0.1362602235},
{"learn":[76.58298873],"iteration":924,"passed_time":1.658348647,"remaining_time":0.1344607011},
{"learn":[76.58145829],"iteration":925,"passed_time":1.659991035,"remaining_time":0.132655871},
{"learn":[76.57471875],"iteration":926,"passed_time":1.661643857,"remaining_time":0.1308522131},
{"learn":[76.57265522],"iteration":927,"passed_time":1.663303714,"remaining_time":0.1290494261},
{"learn":[76.53754729],"iteration":928,"passed_time":1.665053259,"remaining_time":0.1272538013},
{"learn":[76.5180377],"iteration":929,"passed_time":1.666765595,"remaining_time":0.1254554749},
{"learn":[76.49071252],"iteration":930,"passed_time":1.668495041,"remaining_time":0.1236586013},
{"learn":[76.47529277],"iteration":931,"passed_time":1.670201341,"remaining_time":0.1218601837},
{"learn":[76.44857],"iteration":932,"passed_time":1.671948083,"remaining_time":0.1200648677},
{"learn":[76.4426392],"iteration":933,"passed_time":1.673638784,"remaining_time":0.1182656956},
{"learn":[76.44063457],"iteration":934,"passed_time":1.675294932,"remaining_time":0.1164643536},
{"learn":[76.41556413],"iteration":935,"passed_time":1.677036087,"remaining_time":0.1146691342},
{"learn":[76.39999015],"iteration":936,"passed_time":1.679229339,"remaining_time":0.1129044273},
{"learn":[76.39512318],"iteration":937,"passed_time":1.680911576,"remaining_time":0.1111050296},
{"learn":[76.37654645],"iteration":938,"passed_time":1.68267728,"remaining_time":0.1093113036},
{"learn":[76.36933716],"iteration":939,"passed_time":1.684336647,"remaining_time":0.1075108498},
{"learn":[76.34275251],"iteration":940,"passed_time":1.686090796,"remaining_time":0.1057166386},
{"learn":[76.32263103],"iteration":941,"passed_time":1.687823313,"remaining_time":0.1039211806},
{"learn":[76.29616265],"iteration":942,"passed_time":1.6895515,"remaining_time":0.1021255944},
{"learn":[76.29431195],"iteration":943,"passed_time":1.691194238,"remaining_time":0.1003250819},
{"learn":[76.27041604],"iteration":944,"passed_time":1.692932245,"remaining_time":0.09853044815},
{"learn":[76.25684793],"iteration":945,"passed_time":1.694649608,"remaining_time":0.09673475561},
{"learn":[76.23599411],"iteration":946,"passed_time":1.696384219,"remaining_time":0.09494019389},
{"learn":[76.2344184],"iteration":947,"passed_time":1.698026797,"remaining_time":0.09314071039},
{"learn":[76.19852229],"iteration":948,"passed_time":1.699766778,"remaining_time":0.09134679205},
{"learn":[76.17402139],"iteration":949,"passed_time":1.701645663,"remaining_time":0.08956029807},
{"learn":[76.15286221],"iteration":950,"passed_time":1.70336775,"remaining_time":0.08776553077},
{"learn":[76.14600526],"iteration":951,"passed_time":1.705041293,"remaining_time":0.08596846858},
{"learn":[76.12195021],"iteration":952,"passed_time":1.706790141,"remaining_time":0.08417537944},
{"learn":[76.09737361],"iteration":953,"passed_time":1.70867518,"remaining_time":0.08238894997},
{"learn":[76.09553851],"iteration":954,"passed_time":1.710425689,"remaining_time":0.08059597486},
{"learn":[76.08945537],"iteration":955,"passed_time":1.712119412,"remaining_time":0.07880047504},
{"learn":[76.07145398],"iteration":956,"passed_time":1.713873494,"remaining_time":0.07700789993},
{"learn":[76.06400336],"iteration":957,"passed_time":1.715568807,"remaining_time":0.07521282871},
{"learn":[76.04641018],"iteration":958,"passed_time":1.717300639,"remaining_time":0.07341952679},
{"learn":[76.01369298],"iteration":959,"passed_time":1.719012668,"remaining_time":0.07162552783},
{"learn":[75.98274749],"iteration":960,"passed_time":1.720782883,"remaining_time":0.06983406082},
{"learn":[75.95536985],"iteration":961,"passed_time":1.722538549,"remaining_time":0.06804206326},
{"learn":[75.93088788],"iteration":962,"passed_time":1.724271579,"remaining_time":0.06624927146},
{"learn":[75.92934643],"iteration":963,"passed_time":1.72591368,"remaining_time":0.06445320796},
{"learn":[75.9210645],"iteration":964,"passed_time":1.727609909,"remaining_time":0.06265942675},
{"learn":[75.90112013],"iteration":965,"passed_time":1.729317071,"remaining_time":0.06086623232},
{"learn":[75.87295654],"iteration":966,"passed_time":1.731451846,"remaining_time":0.0590878086},
{"learn":[75.8431042],"iteration":967,"passed_time":1.733210812,"remaining_time":0.0572962252},
{"learn":[75.83161158],"iteration":968,"passed_time":1.734917814,"remaining_time":0.05550304669},
{"learn":[75.80835111],"iteration":969,"passed_time":1.736702006,"remaining_time":0.05371243319},
{"learn":[75.79712037],"iteration":970,"passed_time":1.738396403,"remaining_time":0.05191915107},
{"learn":[75.77677293],"iteration":971,"passed_time":1.74012097,"remaining_time":0.05012694153},
{"learn":[75.76290955],"iteration":972,"passed_time":1.741812853,"remaining_time":0.04833396407},
{"learn":[75.72659097],"iteration":973,"passed_time":1.743711938,"remaining_time":0.04654672525},
{"learn":[75.71661291],"iteration":974,"passed_time":1.745467463,"remaining_time":0.04475557597},
{"learn":[75.71089752],"iteration":975,"passed_time":1.747121945,"remaining_time":0.04296201504},
{"learn":[75.70627971],"iteration":976,"passed_time":1.748798733,"remaining_time":0.04116926393},
{"learn":[75.68643297],"iteration":977,"passed_time":1.750531828,"remaining_time":0.03937801658},
{"learn":[75.67817546],"iteration":978,"passed_time":1.752220068,"remaining_time":0.03758592588},
{"learn":[75.67636402],"iteration":979,"passed_time":1.7538879,"remaining_time":0.03579363061},
{"learn":[75.65538028],"iteration":980,"passed_time":1.755635638,"remaining_time":0.03400313672},
{"learn":[75.63908173],"iteration":981,"passed_time":1.757446901,"remaining_time":0.03221389431},
{"learn":[75.63229189],"iteration":982,"passed_time":1.759165044,"remaining_time":0.03042299669},
{"learn":[75.61149078],"iteration":983,"passed_time":1.760915592,"remaining_time":0.02863277386},
{"learn":[75.60994514],"iteration":984,"passed_time":1.76256236,"remaining_time":0.02684105117},
{"learn":[75.60840985],"iteration":985,"passed_time":1.764193763,"remaining_time":0.02504940435},
{"learn":[75.58893783],"iteration":986,"passed_time":1.765911564,"remaining_time":0.02325922019},
{"learn":[75.5745055],"iteration":987,"passed_time":1.767623713,"remaining_time":0.02146911393},
{"learn":[75.56070082],"iteration":988,"passed_time":1.769479978,"remaining_time":0.01968076821},
{"learn":[75.52834418],"iteration":989,"passed_time":1.771229844,"remaining_time":0.01789121054},
{"learn":[75.5209148],"iteration":990,"passed_time":1.772915246,"remaining_time":0.01610114754},
{"learn":[75.49136127],"iteration":991,"passed_time":1.774658501,"remaining_time":0.0143117621},
{"learn":[75.48150757],"iteration":992,"passed_time":1.776384274,"remaining_time":0.01252234634},
{"learn":[75.47984343],"iteration":993,"passed_time":1.778022077,"remaining_time":0.01073252763},
{"learn":[75.47829204],"iteration":994,"passed_time":1.779661377,"remaining_time":0.008943021995},
{"learn":[75.47132713],"iteration":995,"passed_time":1.781331318,"remaining_time":0.007153941036},
{"learn":[75.44450442],"iteration":996,"passed_time":1.783095837,"remaining_time":0.005365383663},
{"learn":[75.42295199],"iteration":997,"passed_time":1.784838423,"remaining_time":0.003576830508},
{"learn":[75.4215577],"iteration":998,"passed_time":1.786488917,"remaining_time":0.001788277194},
{"learn":[75.40366441],"iteration":999,"passed_time":1.788222782,"remaining_time":0}
]}